Workbook

Sheet BANKING_DATASET
A1: BANKING DATASET — RETAIL LOAN DISBURSEMENTS
A2: Business question: How much retail loan value should the bank plan for in the next 6 months?
A4: Month | B4: Month # | C4: Quarter | D4: Actual Loan Disbursement (₹ Cr) | E4: Applications | F4: Approved Loans | G4: Approval Rate | H4: Average Ticket (₹ Lakh) | I4: Branch Network | J4: Comment
A5: 45658 | B5: 1 | C5: Q1 | D5: 1180 | E5: 7200 | F5: 5100 | G5: =F5/E5 | H5: 520 | I5: 205 | J5: Post-year-end normalization
A6: 45689 | B6: 2 | C6: Q1 | D6: 1215 | E6: 7350 | F6: 5230 | G6: =F6/E6 | H6: 525 | I6: 207 | J6: Stable demand
A7: 45717 | B7: 3 | C7: Q1 | D7: 1290 | E7: 7600 | F7: 5480 | G7: =F7/E7 | H7: 528 | I7: 209 | J7: Quarter-end push
A8: 45748 | B8: 4 | C8: Q2 | D8: 1245 | E8: 7420 | F8: 5350 | G8: =F8/E8 | H8: 530 | I8: 210 | J8: New quarter reset
A9: 45778 | B9: 5 | C9: Q2 | D9: 1310 | E9: 7700 | F9: 5560 | G9: =F9/E9 | H9: 534 | I9: 212 | J9: Demand improving
A10: 45809 | B10: 6 | C10: Q2 | D10: 1395 | E10: 8050 | F10: 5850 | G10: =F10/E10 | H10: 538 | I10: 214 | J10: Strong quarter close
A11: 45839 | B11: 7 | C11: Q3 | D11: 1370 | E11: 7980 | F11: 5790 | G11: =F11/E11 | H11: 541 | I11: 216 | J11: Monsoon softness
A12: 45870 | B12: 8 | C12: Q3 | D12: 1425 | E12: 8200 | F12: 6000 | G12: =F12/E12 | H12: 545 | I12: 218 | J12: Demand recovering
A13: 45901 | B13: 9 | C13: Q3 | D13: 1510 | E13: 8500 | F13: 6250 | G13: =F13/E13 | H13: 548 | I13: 220 | J13: Quarter-end strength
A14: 45931 | B14: 10 | C14: Q4 | D14: 1490 | E14: 8450 | F14: 6170 | G14: =F14/E14 | H14: 551 | I14: 222 | J14: Festive demand
A15: 45962 | B15: 11 | C15: Q4 | D15: 1580 | E15: 8800 | F15: 6500 | G15: =F15/E15 | H15: 555 | I15: 224 | J15: Festive demand
A16: 45992 | B16: 12 | C16: Q4 | D16: 1695 | E16: 9300 | F16: 7000 | G16: =F16/E16 | H16: 560 | I16: 226 | J16: Year-end peak
... A22: 46174 | B22: 18 | C22: Q2 | D22: 1885 | E22: 10100 | F22: 7650 | G22: =F22/E22 | H22: 583 | I22: 238 | J22: Strong quarter close

Sheet FORECAST_MODEL
A1: FORECAST MODEL — BANKING LOAN DEMAND
A2: Learn how historical banking data becomes a planning forecast — then challenge the forecast with AI.
A4: 1. HISTORICAL + FORECAST MODEL
A5: Month | B5: Month # | C5: Actual (₹ Cr) | D5: FORECAST.LINEAR | E5: FORECAST.ETS | F5: TREND | G5: 3-Month Moving Avg | H5: Growth vs Prior | I5: Actual / Forecast Flag | J5: Business Meaning | K5: Model Note
A6: 45658 | B6: 1 | C6: =BANKING_DATASET!D5 | D6: =FORECAST.LINEAR(B6,$C$6:$C$23,$B$6:$B$23) | E6: =FORECAST.ETS(A6,$C$6:$C$23,$A$6:$A$23,12,1,1) | F6: =TREND($C$6:$C$23,$B$6:$B$23,B6) | G6: =IF(B6>=3,AVERAGE(INDEX($C:$C,ROW()-2):C6),"") | H6: ="" | I6: Actual | J6: Observed bank performance | K6: Historical actual; formulas illustrate model outputs
A7: 45689 | B7: 2 | C7: =BANKING_DATASET!D6 | D7: =FORECAST.LINEAR(B7,$C$6:$C$23,$B$6:$B$23) | E7: =FORECAST.ETS(A7,$C$6:$C$23,$A$6:$A$23,12,1,1) | F7: =TREND($C$6:$C$23,$B$6:$B$23,B7) | G7: =IF(B7>=3,AVERAGE(INDEX($C:$C,ROW()-2):C7),"") | H7: =IFERROR(C7/C6-1,"") | I7: Actual | J7: Observed bank performance | K7: Historical actual; formulas illustrate model outputs
A8: 45717 | B8: 3 | C8: =BANKING_DATASET!D7 | D8: =FORECAST.LINEAR(B8,$C$6:$C$23,$B$6:$B$23) | E8: =FORECAST.ETS(A8,$C$6:$C$23,$A$6:$A$23,12,1,1) | F8: =TREND($C$6:$C$23,$B$6:$B$23,B8) | G8: =IF(B8>=3,AVERAGE(INDEX($C:$C,ROW()-2):C8),"") | H8: =IFERROR(C8/C7-1,"") | I8: Actual | J8: Observed bank performance | K8: Historical actual; formulas illustrate model outputs
A9: 45748 | B9: 4 | C9: =BANKING_DATASET!D8 | D9: =FORECAST.LINEAR(B9,$C$6:$C$23,$B$6:$B$23) | E9: =FORECAST.ETS(A9,$C$6:$C$23,$A$6:$A$23,12,1,1) | F9: =TREND($C$6:$C$23,$B$6:$B$23,B9) | G9: =IF(B9>=3,AVERAGE(INDEX($C:$C,ROW()-2):C9),"") | H9: =IFERROR(C9/C8-1,"") | I9: Actual | J9: Observed bank performance | K9: Historical actual; formulas illustrate model outputs
A10: 45778 | B10: 5 | C10: =BANKING_DATASET!D9 | D10: =FORECAST.LINEAR(B10,$C$6:$C$23,$B$6:$B$23) | E10: =FORECAST.ETS(A10,$C$6:$C$23,$A$6:$A$23,12,1,1) | F10: =TREND($C$6:$C$23,$B$6:$B$23,B10) | G10: =IF(B10>=3,AVERAGE(INDEX($C:$C,ROW()-2):C10),"") | H10: =IFERROR(C10/C9-1,"") | I10: Actual | J10: Observed bank performance | K10: Historical actual; formulas illustrate model outputs
A11: 45809 | B11: 6 | C11: =BANKING_DATASET!D10 | D11: =FORECAST.LINEAR(B11,$C$6:$C$23,$B$6:$B$23) | E11: =FORECAST.ETS(A11,$C$6:$C$23,$A$6:$A$23,12,1,1) | F11: =TREND($C$6:$C$23,$B$6:$B$23,B11) | G11: =IF(B11>=3,AVERAGE(INDEX($C:$C,ROW()-2):C11),"") | H11: =IFERROR(C11/C10-1,"") | I11: Actual | J11: Observed bank performance | K11: Historical actual; formulas illustrate model outputs
A12: 45839 | B12: 7 | C12: =BANKING_DATASET!D11 | D12: =FORECAST.LINEAR(B12,$C$6:$C$23,$B$6:$B$23) | E12: =FORECAST.ETS(A12,$C$6:$C$23,$A$6:$A$23,12,1,1) | F12: =TREND($C$6:$C$23,$B$6:$B$23,B12) | G12: =IF(B12>=3,AVERAGE(INDEX($C:$C,ROW()-2):C12),"") | H12: =IFERROR(C12/C11-1,"") | I12: Actual | J12: Observed bank performance | K12: Historical actual; formulas illustrate model outputs
A13: 45870 | B13: 8 | C13: =BANKING_DATASET!D12 | D13: =FORECAST.LINEAR(B13,$C$6:$C$23,$B$6:$B$23) | E13: =FORECAST.ETS(A13,$C$6:$C$23,$A$6:$A$23,12,1,1) | F13: =TREND($C$6:$C$23,$B$6:$B$23,B13) | G13: =IF(B13>=3,AVERAGE(INDEX($C:$C,ROW()-2):C13),"") | H13: =IFERROR(C13/C12-1,"") | I13: Actual | J13: Observed bank performance | K13: Historical actual; formulas illustrate model outputs
A14: 45901 | B14: 9 | C14: =BANKING_DATASET!D13 | D14: =FORECAST.LINEAR(B14,$C$6:$C$23,$B$6:$B$23) | E14: =FORECAST.ETS(A14,$C$6:$C$23,$A$6:$A$23,12,1,1) | F14: =TREND($C$6:$C$23,$B$6:$B$23,B14) | G14: =IF(B14>=3,AVERAGE(INDEX($C:$C,ROW()-2):C14),"") | H14: =IFERROR(C14/C13-1,"") | I14: Actual | J14: Observed bank performance | K14: Historical actual; formulas illustrate model outputs
A15: 45931 | B15: 10 | C15: =BANKING_DATASET!D14 | D15: =FORECAST.LINEAR(B15,$C$6:$C$23,$B$6:$B$23) | E15: =FORECAST.ETS(A15,$C$6:$C$23,$A$6:$A$23,12,1,1) | F15: =TREND($C$6:$C$23,$B$6:$B$23,B15) | G15: =IF(B15>=3,AVERAGE(INDEX($C:$C,ROW()-2):C15),"") | H15: =IFERROR(C15/C14-1,"") | I15: Actual | J15: Observed bank performance | K15: Historical actual; formulas illustrate model outputs
A16: 45962 | B16: 11 | C16: =BANKING_DATASET!D15 | D16: =FORECAST.LINEAR(B16,$C$6:$C$23,$B$6:$B$23) | E16: =FORECAST.ETS(A16,$C$6:$C$23,$A$6:$A$23,12,1,1) | F16: =TREND($C$6:$C$23,$B$6:$B$23,B16) | G16: =IF(B16>=3,AVERAGE(INDEX($C:$C,ROW()-2):C16),"") | H16: =IFERROR(C16/C15-1,"") | I16: Actual | J16: Observed bank performance | K16: Historical actual; formulas illustrate model outputs
A17: 45992 | B17: 12 | C17: =BANKING_DATASET!D16 | D17: =FORECAST.LINEAR(B17,$C$6:$C$23,$B$6:$B$23) | E17: =FORECAST.ETS(A17,$C$6:$C$23,$A$6:$A$23,12,1,1) | F17: =TREND($C$6:$C$23,$B$6:$B$23,B17) | G17: =IF(B17>=3,AVERAGE(INDEX($C:$C,ROW()-2):C17),"") | H17: =IFERROR(C17/C16-1,"") | I17: Actual | J17: Observed bank performance | K17: Historical actual; formulas illustrate model outputs
A18: 46023 | B18: 13 | C18: =BANKING_DATASET!D17 | D18: =FORECAST.LINEAR(B18,$C$6:$C$23,$B$6:$B$23) | E18: =FORECAST.ETS(A18,$C$6:$C$23,$A$6:$A$23,12,1,1) | F18: =TREND($C$6:$C$23,$B$6:$B$23,B18) | G18: =IF(B18>=3,AVERAGE(INDEX($C:$C,ROW()-2):C18),"") | H18: =IFERROR(C18/C17-1,"") | I18: Actual | J18: Observed bank performance | K18: Historical actual; formulas illustrate model outputs
... A23: 46174 | B23: 18 | C23: =BANKING_DATASET!D22 | D23: =FORECAST.LINEAR(B23,$C$6:$C$23,$B$6:$B$23) | E23: =FORECAST.ETS(A23,$C$6:$C$23,$A$6:$A$23,12,1,1) | F23: =TREND($C$6:$C$23,$B$6:$B$23,B23) | G23: =IF(B23>=3,AVERAGE(INDEX($C:$C,ROW()-2):C23),"") | H23: =IFERROR(C23/C22-1,"") | I23: Actual | J23: Observed bank performance | K23: Historical actual; formulas illustrate model outputs
A24: 46204 | B24: 19 | D24: =FORECAST.LINEAR(B24,$C$6:$C$23,$B$6:$B$23) | E24: =FORECAST.ETS(A24,$C$6:$C$23,$A$6:$A$23,12,1,1) | F24: =TREND($C$6:$C$23,$B$6:$B$23,B24) | G24: =AVERAGE(C21:C23) | H24: =IFERROR(E24/E23-1,"") | I24: Forecast | J24: Planning estimate for future demand | K24: Compare models before committing capacity
A25: 46235 | B25: 20 | D25: =FORECAST.LINEAR(B25,$C$6:$C$23,$B$6:$B$23) | E25: =FORECAST.ETS(A25,$C$6:$C$23,$A$6:$A$23,12,1,1) | F25: =TREND($C$6:$C$23,$B$6:$B$23,B25) | G25: =AVERAGE(INDEX($C:$C,ROW()-3):C23) | H25: =IFERROR(E25/E24-1,"") | I25: Forecast | J25: Planning estimate for future demand | K25: Compare models before committing capacity
A26: 46266 | B26: 21 | D26: =FORECAST.LINEAR(B26,$C$6:$C$23,$B$6:$B$23) | E26: =FORECAST.ETS(A26,$C$6:$C$23,$A$6:$A$23,12,1,1) | F26: =TREND($C$6:$C$23,$B$6:$B$23,B26) | G26: =AVERAGE(INDEX($C:$C,ROW()-3):C23) | H26: =IFERROR(E26/E25-1,"") | I26: Forecast | J26: Planning estimate for future demand | K26: Compare models before committing capacity
A27: 46296 | B27: 22 | D27: =FORECAST.LINEAR(B27,$C$6:$C$23,$B$6:$B$23) | E27: =FORECAST.ETS(A27,$C$6:$C$23,$A$6:$A$23,12,1,1) | F27: =TREND($C$6:$C$23,$B$6:$B$23,B27) | G27: =AVERAGE(INDEX($C:$C,ROW()-3):C23) | H27: =IFERROR(E27/E26-1,"") | I27: Forecast | J27: Planning estimate for future demand | K27: Compare models before committing capacity
A28: 46327 | B28: 23 | D28: =FORECAST.LINEAR(B28,$C$6:$C$23,$B$6:$B$23) | E28: =FORECAST.ETS(A28,$C$6:$C$23,$A$6:$A$23,12,1,1) | F28: =TREND($C$6:$C$23,$B$6:$B$23,B28) | G28: =AVERAGE(INDEX($C:$C,ROW()-3):C23) | H28: =IFERROR(E28/E27-1,"") | I28: Forecast | J28: Planning estimate for future demand | K28: Compare models before committing capacity
A29: 46357 | B29: 24 | D29: =FORECAST.LINEAR(B29,$C$6:$C$23,$B$6:$B$23) | E29: =FORECAST.ETS(A29,$C$6:$C$23,$A$6:$A$23,12,1,1) | F29: =TREND($C$6:$C$23,$B$6:$B$23,B29) | G29: =AVERAGE(INDEX($C:$C,ROW()-3):C23) | H29: =IFERROR(E29/E28-1,"") | I29: Forecast | J29: Planning estimate for future demand | K29: Compare models before committing capacity
A32: 2. WHAT EACH FORECAST FORMULA IS TEACHING
A33: Method | B33: What it does | C33: When to use it
A34: FORECAST.LINEAR | B34: Predicts a future value using a straight-line trend from historical values. | H34: Good starting point when the series has a fairly stable linear trend.
A35: FORECAST.ETS | B35: Uses exponential smoothing and can capture level, trend and seasonality. | H35: Useful when banking demand has recurring seasonal patterns.
A36: TREND | B36: Returns values along a linear trend line. | H36: Useful for understanding the underlying direction of demand.
A37: 3-Month Moving Average | B37: Average of recent months. | H37: Simple baseline; useful for short-term operational planning.
A38: Growth % | B38: Current forecast ÷ previous period − 1. | H38: Converts the forecast into a business growth signal.
A41: 3. BANKING DECISION — MODEL COMPARISON
A42: Future Month | B42: Linear Forecast | C42: ETS Forecast | D42: Trend Forecast | E42: Planning View | F42: Why
A43: =A24 | B43: =D24 | C43: =E24 | D43: =F24 | E43: =AVERAGE(B43:D43) | F43: Use the average as a neutral planning baseline; investigate large model differences.
A44: =A25 | B44: =D25 | C44: =E25 | D44: =F25 | E44: =AVERAGE(B44:D44) | F44: Use the average as a neutral planning baseline; investigate large model differences.
A45: =A26 | B45: =D26 | C45: =E26 | D45: =F26 | E45: =AVERAGE(B45:D45) | F45: Use the average as a neutral planning baseline; investigate large model differences.
A46: =A27 | B46: =D27 | C46: =E27 | D46: =F27 | E46: =AVERAGE(B46:D46) | F46: Use the average as a neutral planning baseline; investigate large model differences.
A47: =A28 | B47: =D28 | C47: =E28 | D47: =F28 | E47: =AVERAGE(B47:D47) | F47: Use the average as a neutral planning baseline; investigate large model differences.
A48: =A29 | B48: =D29 | C48: =E29 | D48: =F29 | E48: =AVERAGE(B48:D48) | F48: Use the average as a neutral planning baseline; investigate large model differences.

Sheet FORECAST_STORY
A1: BANKING FORECAST — FROM DATA TO DECISION
A3: THE BUSINESS PROBLEM
A4: A bank needs to plan branch staffing, loan-processing capacity, liquidity and marketing before demand arrives. Historical loan disbursements show the pattern, but management needs a forward-looking estimate for the next six months.
A9: WHAT THE LEARNER SHOULD NOTICE
A10: 1. Actual data is the evidence — never replace it with a forecast.
A11: 2. Linear forecasting answers: 'What if the current direction continues?'
A12: 3. ETS answers: 'What if trend + recurring seasonal behaviour continue?'
A13: 4. Moving average provides a simple benchmark.
A14: 5. If models disagree materially, investigate the reason before acting.
A15: 6. Forecasts support decisions; they do not guarantee the future.
A18: BANKING USE CASES
A19: Area | B19: Business Use
A20: Loan demand | B20: Plan credit officers, processing capacity and branch staffing.
A21: Cash / liquidity | B21: Prepare funding requirements for expected disbursements.
A22: Marketing | B22: Time campaigns around expected demand peaks.
A23: Risk planning | B23: Stress-test whether rapid growth could create operational pressure.
A26: AI — HOW TO USE IT SMARTLY
A27: ✓ AI can detect patterns and seasonality you may overlook.
A28: ✓ AI can compare Linear vs ETS vs Moving Average and explain the difference.
A29: ✓ AI can challenge assumptions and identify missing drivers.
A30: ✓ AI can convert the forecast into an executive business narrative.
A31: ✓ AI should NOT invent future numbers or be trusted without checking the Excel model.
A34: FINAL DECISION FRAMEWORK
A35: Step | B35: Action | C35: Question
A36: 1 | B36: Observe | C36: What does the historical series actually show?
A37: 2 | B37: Model | C37: Generate at least two forecasting approaches.
A38: 3 | B38: Compare | C38: Check whether models agree or diverge.
A39: 4 | B39: Validate | C39: Measure errors on known historical periods where possible.
A40: 5 | B40: Decide | C40: Use the forecast to plan capacity, liquidity and campaigns.
A41: 6 | B41: Review | C41: Update the forecast when new actual data arrives.

Sheet AI_GUIDE
A1: AI GUIDE — FORECASTING WITH A BANKING DATASET
A3: COPY-READY PROMPTS
A4: Prompt | B4: Use with your dataset
A5: 1 • Explore | B5: Analyze this banking loan-disbursement dataset. Identify trend, seasonality, outliers and structural changes. Use exact months and numbers.
A6: 2 • Compare | B6: Compare FORECAST.LINEAR, FORECAST.ETS and a 3-month moving average. Explain why the forecasts differ and which method is more appropriate for this dataset.
A7: 3 • Challenge | B7: Act as a skeptical banking CFO. Challenge the forecast. What assumptions could make it wrong? What external variables should we consider?
A8: 4 • Scenario | B8: Create Base, Upside and Downside scenarios for the next six months. Clearly label assumptions and do not invent historical facts.
A9: 5 • Story | B9: Turn the validated forecast into an executive story: What is expected? Why? What is the business impact? What should management do?
A10: 6 • Action | B10: Based only on the validated forecast, recommend actions for staffing, liquidity, marketing and branch capacity.
A13: AI SAFETY RULES FOR FORECASTING
A14: ⚠ Never treat an AI-generated number as evidence until it can be reproduced in Excel.
A15: ⚠ Separate historical facts, model output, assumptions and recommendations.
A16: ⚠ Ask AI to show the formula or calculation logic.
A17: ⚠ Validate unusual forecast jumps against business events.
A18: ⚠ Use multiple methods when the decision is financially important.
A21: LEARNER ACTIVITY
A22: 1. Open BANKING_DATASET and inspect the 18 months of actual loan disbursement data.
A23: 2. Open FORECAST_MODEL and identify the formulas in the historical and future rows.
A24: 3. Compare Linear, ETS, Trend and Moving Average forecasts for Jul–Dec 2026.
A25: 4. Decide which forecast you would use for bank planning and explain why.
A26: 5. Use one AI prompt from this sheet to challenge your decision.
A27: 6. Write a final management recommendation in 5–7 sentences.
