Workbook

Sheet START_HERE
A1: LEVEL 5 • CHAPTER 1 — AI-POWERED BUSINESS PROBLEM SOLVING
A3: Learning objective | B3: Move from a vague business problem → analytical questions → KPIs → data requirements → AI hypotheses → validated analysis plan.
A5: HOW TO USE THIS WORKBOOK
A6: 1. Study the two handwritten visual pages for this chapter.
A7: 2. Complete Example_1_Practice: retail — 'Sales are down. Please analyze.'
A8: 3. Complete Example_2_Practice: e-commerce — quarterly sales decline.
A9: 4. Use AI_Prompt_Tracks to practice asking AI better analytical questions.
A10: 5. Validate every AI suggestion against the workbook data.
A11: 6. Use the Solution sheets only after attempting the work.
A12: 7. Finish Capstone_Checklist and explain the reasoning in your own words.
A14: THE AI-POWERED PROBLEM-SOLVING FRAMEWORK
A15: Step | B15: Stage | C15: What to do
A16: 01 | B16: Business Problem | C16: Define what happened and what decision is needed.
A17: 02 | B17: Understand | C17: Clarify scope, period, context and success criteria.
A18: 03 | B18: Analytical Questions | C18: Ask questions that can reveal the cause.
A19: 04 | B19: KPIs | C19: Choose measures that prove/disprove hypotheses.
A20: 05 | B20: Data Requirements | C20: Identify tables, fields, dimensions and periods.
A21: 06 | B21: AI Collaboration | C21: Use AI for hypotheses, angles and challenge questions.
A22: 07 | B22: Analysis Plan | C22: Sequence the work and expected outputs.
A25: IMPORTANT | B25: AI suggestion ≠ validated finding. Every number and causal statement must be checked against real data.

Sheet Example_1_Practice
A1: EXAMPLE 1 — RETAIL SALES: 'SALES ARE DOWN. PLEASE ANALYZE.'
A2: Situation | B2: Management has noticed weaker sales and wants to know what changed, why, and where to act.
A4: PRACTICE TASK
A5: 1. Define the problem in one precise sentence.
A6: 2. Write 5 analytical questions.
A7: 3. Select KPIs: Total Sales, Growth %, Average Selling Price, Units Sold, Gross Margin %, Customer Contribution.
A8: 4. Identify required data, dimensions and time period.
A9: 5. Ask AI for 5 hypotheses; label them hypotheses, not findings.
A10: 6. Build a 5-step analysis plan with expected outputs.
A13: Month | B13: Region | C13: Channel | D13: Product | E13: Units | F13: Sales | G13: Cost | H13: Customers
A14: 45658 | B14: North | C14: Retail | D14: Laptop | E14: 71 | F14: 5103837.6 | G14: 3833330.3 | H14: 25
A15: 45658 | B15: North | C15: Online | D15: Monitor | E15: 135 | F15: 2417092.2 | G15: 1802725.4 | H15: 49
A16: 45658 | B16: North | C16: Distributor | D16: Keyboard | E16: 94 | F16: 384070.68 | G16: 267109.83 | H16: 44
A17: 45658 | B17: North | C17: Online | D17: Headset | E17: 60 | F17: 157408.65 | G17: 119066.02 | H17: 35
A18: 45658 | B18: North | C18: Online | D18: Printer | E18: 45 | F18: 597138.17 | G18: 473836.7 | H18: 23
A19: 45658 | B19: South | C19: Retail | D19: Laptop | E19: 37 | F19: 2418991.8 | G19: 1817636.4 | H19: 23
A20: 45658 | B20: South | C20: Online | D20: Monitor | E20: 35 | F20: 630188.7 | G20: 443634.86 | H20: 16
A21: 45658 | B21: South | C21: Distributor | D21: Keyboard | E21: 99 | F21: 392843.64 | G21: 288947 | H21: 58
A22: 45658 | B22: South | C22: Online | D22: Headset | E22: 53 | F22: 139574.18 | G22: 109261.01 | H22: 21
A23: 45658 | B23: South | C23: Online | D23: Printer | E23: 42 | F23: 502937.07 | G23: 347681.41 | H23: 15
A24: 45658 | B24: West | C24: Distributor | D24: Laptop | E24: 56 | F24: 3581876.2 | G24: 2778495.9 | H24: 32
A25: 45658 | B25: West | C25: Retail | D25: Monitor | E25: 89 | F25: 1614978.9 | G25: 1229924.6 | H25: 39
... A133: 45809 | B133: East | C133: Distributor | D133: Printer | E133: 48 | F133: 551731.98 | G133: 379315.77 | H133: 17

Sheet Example_1_Analysis
A1: EXAMPLE 1 — GUIDED ANALYSIS TRACK
A3: TRACK 1 — DEFINE THE PROBLEM
A4: Question | B4: Your answer | C4: AI prompt | D4: Good answer
A5: What exactly is down? | C5: Turn 'sales are down' into measurable business questions. | D5: Metric + period + comparison.
A6: Compared with what? | C6: Suggest useful comparison baselines. | D6: Prior period / target / budget / prior year.
A7: Where might the decline sit? | C7: Suggest dimensions for diagnosing retail sales. | D7: Time, region, channel, product, customer.
A9: TRACK 2 — KPI CHECKLIST
A10: KPI | B10: Why it matters | C10: Formula / logic | D10: Your interpretation
A11: Total Sales | B11: Overall output | C11: SUM(Sales)
A12: Sales Growth % | B12: Direction of change | C12: (Current-Prior)/Prior
A13: Average Selling Price | B13: Price/mix signal | C13: Sales / Units
A14: Units Sold | B14: Volume signal | C14: SUM(Units)
A15: Gross Margin % | B15: Profitability | C15: (Sales-Cost)/Sales
A16: Customer Contribution | B16: Customer impact | C16: Sales by customer/segment
A18: TRACK 3 — ANALYSIS PLAN
A19: Step | B19: Analysis | C19: Tool / AI support | D19: Expected output
A20: 1 | B20: Overall performance | C20: Excel / Power BI / AI | D20: Where did sales change?
A21: 2 | B21: Dimension drill-down | C21: Pivot / Power BI / AI | D21: Worst regions/products/channels
A22: 3 | B22: Volume vs price/mix | C22: Excel / SQL | D22: Main driver
A23: 4 | B23: Customer contribution | C23: Pivot / SQL / AI | D23: Segments driving change
A24: 5 | B24: Root cause + action | C24: AI + validated numbers | D24: Evidence-backed recommendation

Sheet Example_1_Solution
A1: EXAMPLE 1 — MODEL SOLUTION
A3: MODEL PROBLEM STATEMENT
A4: Weak | B4: Sales are down.
A5: Better | B5: Retail sales have declined versus a defined comparison period; management needs the largest drivers by time, region, channel and product and evidence-backed recovery actions.
A8: MODEL ANALYTICAL QUESTIONS
A9: • Which period shows the largest decline?
A10: • Which region contributes most?
A11: • Which products lost units?
A12: • Is movement driven by volume, price/mix or channel mix?
A13: • Which customer segments contribute most?
A14: • Did gross margin deteriorate?
A16: AI HYPOTHESES — MUST BE VALIDATED
A17: • Decline may be concentrated in one region.
A18: • A product may have lost units while price stayed stable.
A19: • Channel mix may have shifted.
A20: • Gross margin may have fallen because of discounting or mix.
... A24: QUICK NUMERIC CHECKS
A25: Total Sales | B25: =SUM(Example_1_Practice!F14:F133)
A26: Total Units | B26: =SUM(Example_1_Practice!E14:E133)
A27: Gross Margin % | B27: =(SUM(Example_1_Practice!F14:F133)-SUM(Example_1_Practice!G14:G133))/SUM(Example_1_Practice!F14:F133)

Sheet Example_2_Practice
A1: EXAMPLE 2 — E-COMMERCE: 15% QUARTERLY SALES DECLINE
A2: Situation | B2: Online store sales fell in the last quarter versus the previous quarter. Management wants the reasons and recovery actions.
A4: PRACTICE TASK
A5: 1. Confirm the sales decline.
A6: 2. Check traffic, orders, AOV and conversion.
A7: 3. Drill into product/category, customer type, region, channel, campaign and device.
A8: 4. Check returns and out-of-stock rates.
A9: 5. Generate AI hypotheses, then validate each with numbers.
A10: 6. Build a 5-step recovery analysis plan.
A13: Month | B13: Quarter | C13: Traffic | D13: Orders | E13: AOV | F13: Sales | G13: New Customers | H13: Repeat Customers | I13: Conversion Rate | J13: Return Rate | K13: Out of Stock Rate
A14: Jan-26 | B14: Q1 | C14: 120000 | D14: 3600 | E14: 100 | F14: 360000 | G14: 1500 | H14: 2100 | I14: 0.03 | J14: 0.04 | K14: 0.03
A15: Feb-26 | B15: Q1 | C15: 125000 | D15: 3750 | E15: 100 | F15: 375000 | G15: 1600 | H15: 2150 | I15: 0.03 | J15: 0.04 | K15: 0.03
A16: Mar-26 | B16: Q1 | C16: 130000 | D16: 3900 | E16: 100 | F16: 390000 | G16: 1650 | H16: 2250 | I16: 0.03 | J16: 0.04 | K16: 0.03
A17: Apr-26 | B17: Q2 | C17: 124000 | D17: 3600 | E17: 100 | F17: 360000 | G17: 1450 | H17: 2150 | I17: 0.029 | J17: 0.05 | K17: 0.05
A18: May-26 | B18: Q2 | C18: 118000 | D18: 3400 | E18: 100 | F18: 340000 | G18: 1350 | H18: 2050 | I18: 0.029 | J18: 0.06 | K18: 0.07
A19: Jun-26 | B19: Q2 | C19: 111000 | D19: 3190 | E19: 100 | F19: 319000 | G19: 1250 | H19: 1940 | I19: 0.029 | J19: 0.07 | K19: 0.09
A22: TRANSACTION DATA FOR DRILL-DOWN
A23: Date | B23: Product | C23: Category | D23: Customer Type | E23: Region | F23: Channel | G23: Campaign | H23: Device | I23: Units | J23: Sales | K23: Returns | L23: OutOfStock
A24: 46030 | B24: Laptop | C24: Electronics | D24: New | E24: East | F24: Organic | G24: Search | H24: Desktop | I24: 2 | J24: 113561.8 | K24: 0 | L24: 0
A25: 46028 | B25: Mixer | C25: Home | D25: Existing | E25: North | F25: Direct | G25: Search | H25: Desktop | I25: 5 | J25: 22146.83 | K25: 0 | L25: 0
A26: 46046 | B26: Mixer | C26: Home | D26: New | E26: West | F26: Direct | G26: Email | H26: Desktop | I26: 3 | J26: 14733.14 | K26: 0 | L26: 0
A27: 46039 | B27: Chair | C27: Home | D27: New | E27: West | F27: Paid | G27: Social | H27: Desktop | I27: 1 | J27: 5810.9 | K27: 0 | L27: 0
A28: 46039 | B28: Shoes | C28: Fashion | D28: Existing | E28: East | F28: Paid | G28: Social | H28: Desktop | I28: 6 | J28: 20568.3 | K28: 1 | L28: 0
A29: 46040 | B29: Mixer | C29: Home | D29: Existing | E29: East | F29: Organic | G29: Search | H29: Desktop | I29: 6 | J29: 24832.28 | K29: 0 | L29: 0
A30: 46039 | B30: Laptop | C30: Electronics | D30: New | E30: East | F30: Organic | G30: Search | H30: Desktop | I30: 4 | J30: 224227 | K30: 0 | L30: 0
A31: 46034 | B31: Shoes | C31: Fashion | D31: New | E31: East | F31: Organic | G31: Search | H31: Mobile | I31: 4 | J31: 14435.62 | K31: 0 | L31: 0
A32: 46049 | B32: Phone | C32: Electronics | D32: New | E32: East | F32: Organic | G32: Search | H32: Desktop | I32: 3 | J32: 76268.15 | K32: 0 | L32: 0
A33: 46038 | B33: T-Shirt | C33: Fashion | D33: New | E33: West | F33: Organic | G33: Email | H33: Mobile | I33: 1 | J33: 1124.84 | K33: 0 | L33: 0
A34: 46028 | B34: Phone | C34: Electronics | D34: Existing | E34: West | F34: Organic | G34: Search | H34: Mobile | I34: 4 | J34: 97045.58 | K34: 0 | L34: 0
A35: 46038 | B35: Shoes | C35: Fashion | D35: New | E35: South | F35: Organic | G35: Email | H35: Mobile | I35: 8 | J35: 28663.28 | K35: 0 | L35: 0
... A203: 46191 | B203: Phone | C203: Electronics | D203: New | E203: South | F203: Direct | G203: None | H203: Mobile | I203: 8 | J203: 166503.4 | K203: 0 | L203: 0

Sheet Example_2_Analysis
A1: EXAMPLE 2 — STEP-BY-STEP AI-POWERED ANALYSIS TRACK
A3: STEP 1 — CONFIRM THE PROBLEM
A4: Check | B4: Approach | C4: What to look for | D4: Your finding
A5: Q1 vs Q2 Sales | B5: SUM by quarter | C5: Confirm decline
A6: Traffic change | B6: Q1 vs Q2 | C6: Top-of-funnel effect
A7: Orders change | B7: Q1 vs Q2 | C7: Demand effect
A8: AOV change | B8: Q1 vs Q2 | C8: Basket value effect
A9: Conversion change | B9: Orders / Traffic | C9: Funnel efficiency
A10: Return / stock change | B10: Compare rates | C10: Operational causes
A12: STEP 2 — KEY QUESTIONS
A13: 01. Which category contributed most?
A14: 02. Are new customers declining faster?
A15: 03. Which region has the largest movement?
A16: 04. Is the decline concentrated by channel?
A17: 05. Is Mobile conversion weaker?
A18: 06. Did returns increase?
A19: 07. Did stock-outs rise?
A20: 08. Could price/mix explain the change?
A22: STEP 3 — AI HYPOTHESIS TRACKER
A23: Hypothesis | B23: Evidence to check | C23: KPI / data | D23: AI prompt | E23: Validated? | F23: Conclusion
A24: Traffic decline | B24: Traffic vs orders | C24: Traffic, Orders | D24: Suggest evidence for/against this hypothesis.
A25: Conversion weakened | B25: Orders / traffic | C25: Conversion | D25: Compare Q1 and Q2 conversion and possible causes.
A26: Stock-outs hurt sales | B26: Stock-outs vs sales | C26: OutOfStock, Sales | D26: Identify products where stock-outs may explain lost sales.
A27: Returns increased | B27: Returns by category | C27: Return Rate | D27: Assess whether returns materially affect performance.
A28: Customer mix changed | B28: New vs existing | C28: Customer Type | D28: Compare customer-type movement and contribution.
A30: STEP 4 — ANALYSIS PLAN
A31: Step | B31: Analysis | C31: Tool / AI support | D31: Expected output
A32: 1 | B32: Quarter KPI bridge | C32: Excel / Power BI / AI | D32: Confirm size of decline
A33: 2 | B33: Funnel analysis | C33: Excel / Power BI / AI | D33: Traffic → Orders → Conversion
A34: 3 | B34: Dimension drill-down | C34: Pivot / SQL / AI | D34: Worst category/region/channel/device
A35: 4 | B35: Operational checks | C35: Returns + stock-outs | D35: Non-marketing causes
A36: 5 | B36: Root cause + action | C36: AI + validated evidence | D36: Prioritized recovery actions

Sheet Example_2_Solution
A1: EXAMPLE 2 — MODEL SOLUTION & VALIDATION
A3: QUARTER KPI CHECK
A4: Metric | B4: Q1 | C4: Q2 | D4: Change % | E4: Interpretation
A5: Sales | B5: =SUM(Example_2_Practice!F14:F16) | C5: =SUM(Example_2_Practice!F17:F19) | D5: =(C5-B5)/B5 | E5: Sales falls by about 15%.
A6: Traffic | B6: =SUM(Example_2_Practice!C14:C16) | C6: =SUM(Example_2_Practice!C17:C19) | D6: =(C6-B6)/B6 | E6: Traffic declines.
A7: Orders | B7: =SUM(Example_2_Practice!D14:D16) | C7: =SUM(Example_2_Practice!D17:D19) | D7: =(C7-B7)/B7 | E7: Orders decline.
A8: AOV | B8: =AVERAGE(Example_2_Practice!E14:E16) | C8: =AVERAGE(Example_2_Practice!E17:E19) | D8: =(C8-B8)/B8 | E8: AOV is stable; not the primary driver.
A9: Conversion | B9: =AVERAGE(Example_2_Practice!I14:I16) | C9: =AVERAGE(Example_2_Practice!I17:I19) | D9: =(C9-B9)/B9 | E9: Conversion weakens slightly.
A10: Return Rate | B10: =AVERAGE(Example_2_Practice!J14:J16) | C10: =AVERAGE(Example_2_Practice!J17:J19) | D10: =(C10-B10)/B10 | E10: Returns increase.
A11: Out-of-Stock | B11: =AVERAGE(Example_2_Practice!K14:K16) | C11: =AVERAGE(Example_2_Practice!K17:K19) | D11: =(C11-B11)/B11 | E11: Stock-outs rise substantially.
A14: MODEL CONCLUSION
A15: • Sales decline is real in the designed example.
A16: • Traffic and orders decline, so the funnel should be investigated.
A17: • AOV remains stable, so lower basket value is not the strongest explanation.
A18: • Conversion weakens, providing a second possible driver.
A19: • Return and stock-out rates rise, so operational causes must be tested.
A20: • Professional conclusion: state what the data supports and keep unvalidated causes as hypotheses.
A22: EXECUTIVE SUMMARY TEMPLATE
A23: Situation | B23: E-commerce sales declined in Q2 versus Q1.
A24: Evidence | B24: Traffic and orders declined, AOV stayed stable, conversion weakened, and operational indicators worsened.
A25: Likely drivers | B25: Top-of-funnel weakness plus conversion and operational issues are stronger hypotheses than AOV decline.
A26: Next action | B26: Drill into channel, device, category and stock-out segments and quantify contribution before recommending recovery actions.

Sheet AI_Prompt_Tracks
A1: AI PROMPT TRACKS — LEARN TO THINK WITH AI
A3: Track | B3: Goal | C3: Prompt | D3: Expected output | E3: Human verification
A4: 01 Clarify | B4: Turn vague request into a measurable problem | C4: Act as a senior business analyst. Turn 'sales are down' into a precise problem statement and ask only key clarification questions. | D4: Clear scope, period, comparison, decision. | E4: Check AI did not invent context.
A5: 02 Questions | B5: Create analytical questions | C5: Create 8 questions that could reveal the root cause, grouped by volume, price, mix, customer, channel and operations. | D5: Question framework. | E5: Keep only answerable questions.
A6: 03 KPIs | B6: Choose measurable metrics | C6: For each hypothesis, suggest KPI, definition, formula and interpretation risk. | D6: KPI dictionary. | E6: Confirm fields exist.
A7: 04 Data | B7: Define data requirements | C7: List tables, fields, dimensions, time period and quality checks needed. | D7: Data requirements map. | E7: Verify source availability.
A8: 05 Hypotheses | B8: Generate possible causes | C8: Generate 5–7 testable hypotheses and state evidence needed to prove/disprove each. | D8: Hypothesis list. | E8: Validate with data.
A9: 06 Analysis plan | B9: Sequence the work | C9: Create a 5-step analysis plan with calculation, tool, expected output and decision supported. | D9: Prioritized plan. | E9: Check feasibility.
A10: 07 Challenge | B10: Stress-test a finding | C10: Here is my finding and numbers: [paste]. Challenge it. What alternative explanations or missing evidence should I test? | D10: Skeptical review. | E10: Check against data.
A11: 08 Executive story | B11: Communicate validated findings | C11: Create a 1-page executive summary: situation, evidence, root cause, impact, recommendation and next action. Do not invent numbers. | D11: Decision-ready summary. | E11: Verify every number.
A14: AI QUALITY RULES
A15: ✓ AI suggestion ≠ finding.
A16: ✓ Every number must be traceable.
A17: ✓ Every KPI needs a definition.
A18: ✓ Test alternative explanations.
A19: ✓ Validate data quality before conclusions.
A20: ✓ Do not expose confidential data to unapproved AI tools.
A21: ✓ Human analyst owns the final conclusion.

Sheet Capstone_Checklist
A1: CHAPTER 1 — PROFESSIONAL MASTERY CHECKLIST
A3: Capability | B3: Done? | C3: Evidence / notes
A4: Define a vague business problem | B4: ☐
A5: Clarify scope, period and decision | B5: ☐
A6: Create analytical questions | B6: ☐
A7: Select appropriate KPIs | B7: ☐
A8: Identify data requirements | B8: ☐
A9: Use AI to generate hypotheses | B9: ☐
A10: Validate AI suggestions | B10: ☐
A11: Build analysis sequence | B11: ☐
A12: Distinguish root cause from correlation | B12: ☐
A13: Recommend next analysis/action | B13: ☐
A14: Write an evidence-backed executive summary | B14: ☐
A17: FINAL TEST
A18: Without looking at the Solution sheets, take either business problem and explain: Problem → Questions → KPIs → Data → Hypotheses → Analysis Plan → Expected Decision.
