Workbook
Name Cities_All: 'MASTER DATA'!$N$21:$N$44
Name Cities_Assam: 'MASTER DATA'!$Z$21:$Z$22
Name Cities_Delhi: 'MASTER DATA'!$O$21:$O$22
Name Cities_Gujarat: 'MASTER DATA'!$V$21:$V$22
Name Cities_Haryana: 'MASTER DATA'!$P$21:$P$22
Name Cities_Karnataka: 'MASTER DATA'!$R$21:$R$22
Name Cities_Maharashtra: 'MASTER DATA'!$U$21:$U$22
Name Cities_Odisha: 'MASTER DATA'!$Y$21:$Y$22
Name Cities_Rajasthan: 'MASTER DATA'!$W$21:$W$22
Name Cities_Tamil_Nadu: 'MASTER DATA'!$S$21:$S$22
Name Cities_Telangana: 'MASTER DATA'!$T$21:$T$22
Name Cities_Uttar_Pradesh: 'MASTER DATA'!$Q$21:$Q$22
Name Cities_West_Bengal: 'MASTER DATA'!$X$21:$X$22
Name DashboardTrendMonths: OFFSET(DASHBOARD!$G$20,0,0,8,1)
Name DashboardTrendValues: OFFSET(DASHBOARD!$H$20,0,0,8,1)
Name MetricList: 'MASTER DATA'!$J$5:$J$8
Name PeriodList: 'MASTER DATA'!$L$5:$L$7
Name RegionList: 'MASTER DATA'!$F$5:$F$9
Name ScenarioList: 'MASTER DATA'!$H$5:$H$7
Name States_All: 'MASTER DATA'!$N$5:$N$16
Name States_East: 'MASTER DATA'!$R$5:$R$7
Name States_North: 'MASTER DATA'!$O$5:$O$7
Name States_South: 'MASTER DATA'!$P$5:$P$7
Name States_West: 'MASTER DATA'!$Q$5:$Q$7

Sheet README
A1: LEVEL 3 • SESSION 1 — ADVANCED FORMULAS DYNAMIC DASHBOARD
A2: Professional capstone using the five chapters together.
A4: Component | B4: Included | C4: Purpose
A5: RAW DATA | B5: 1,500 transactions | C5: Realistic source layer for interactive filtering.
A6: MASTER DATA | B6: Products, cities, managers, validation lists and named ranges | C6: Supports lookups and dependent validation.
A7: DASHBOARD | B7: Controls, KPI cards, trend, product chart, category mix and lookup insights | C7: Shows formulas becoming a usable analytical product.
A8: FORMULA LAB | B8: Five functions + combination patterns + cautions | C8: Connects syntax to design decisions.
A9: PRACTICE | B9: Rebuild tasks + stress/performance thinking | C9: Forces application rather than copying.
A13: THE FIVE CHAPTERS
A14: • | B14: Chapter 1 — INDEX + MATCH (Advanced)
A15: • | B15: Chapter 2 — XLOOKUP (Advanced)
A16: • | B16: Chapter 3 — OFFSET
A17: • | B17: Chapter 4 — INDIRECT
A18: • | B18: Chapter 5 — CHOOSE + MATCH + INDEX combinations
A21: HOW TO USE
A22: Open DASHBOARD, change the yellow/orange controls, and observe the KPI and chart logic. Then use PRACTICE to rebuild the same architecture yourself.

Sheet DASHBOARD
A1: ADVANCED DYNAMIC SALES DASHBOARD
A2: Interactive controls + dynamic formulas from all five Level 3 Session 1 chapters.
A4: DASHBOARD CONTROLS | E4: DATE WINDOW
A5: Scenario | B5: Actual | E5: Start Date | F5: 46023
A6: Region | B6: All | E6: End Date | F6: 46265
A7: State | B7: All | E7: Tip | F7: Change inputs; KPIs and charts react.
A8: City | B8: All
A9: Category | B9: All
A10: Metric | B10: Sales
A11: Period | B11: YTD
A13: TOTAL SALES | C13: TOTAL PROFIT | E13: TOTAL UNITS | G13: AVG ORDER VALUE | I13: TOP PRODUCT | K13: PROFIT MARGIN | M13: SELECTED METRIC
A14: =SUMIFS('RAW DATA'!$K$5:$K$1504,'RAW DATA'!$B$5:$B$1504,$B$5,'RAW DATA'!$C$5:$C$1504,IF($B$6="All","<>",$B$6),'RAW DATA'!$D$5:$D$1504,IF($B$7="All","<>",$B$7),'RAW DATA'!$E$5:$E$1504,IF($B$8="All","<>",$B$8),'RAW DATA'!$F$5:$F$1504,IF($B$9="All","<>",$B$9),'RAW DATA'!$A$5:$A$1504,">="&$F$5,'RAW DATA'!$A$5:$A$1504,"<="&$F$6) -> 195949354 | C14: =SUMIFS('RAW DATA'!$M$5:$M$1504,'RAW DATA'!$B$5:$B$1504,$B$5,'RAW DATA'!$C$5:$C$1504,IF($B$6="All","<>",$B$6),'RAW DATA'!$D$5:$D$1504,IF($B$7="All","<>",$B$7),'RAW DATA'!$E$5:$E$1504,IF($B$8="All","<>",$B$8),'RAW DATA'!$F$5:$F$1504,IF($B$9="All","<>",$B$9),'RAW DATA'!$A$5:$A$1504,">="&$F$5,'RAW DATA'!$A$5:$A$1504,"<="&$F$6) -> 54555307 | E14: =SUMIFS('RAW DATA'!$J$5:$J$1504,'RAW DATA'!$B$5:$B$1504,$B$5,'RAW DATA'!$C$5:$C$1504,IF($B$6="All","<>",$B$6),'RAW DATA'!$D$5:$D$1504,IF($B$7="All","<>",$B$7),'RAW DATA'!$E$5:$E$1504,IF($B$8="All","<>",$B$8),'RAW DATA'!$F$5:$F$1504,IF($B$9="All","<>",$B$9),'RAW DATA'!$A$5:$A$1504,">="&$F$5,'RAW DATA'!$A$5:$A$1504,"<="&$F$6) -> 10909 | G14: =IFERROR(A14/E14,0) -> 17962.174 | I14: =INDEX($J$18:$J$33,MATCH(MAX($K$18:$K$33),$K$18:$K$33,0)) -> Laptop Pro | K14: =IFERROR(C14/A14,0) -> 0.27841534 | M14: =CHOOSE(MATCH($B$10,{"Sales","Profit","Units"},0),A14,C14,E14) -> 195949354
J17: Product | K17: Sales | L17: Profit | M17: Units
A18: XLOOKUP — TOP PRODUCT METADATA | D18: INDEX + MATCH — SELECTED CITY | G18: OFFSET — DYNAMIC TREND SOURCE | J18: Laptop Pro | K18: =SUMIFS('RAW DATA'!$K$5:$K$1504,'RAW DATA'!$B$5:$B$1504,$B$5,'RAW DATA'!$C$5:$C$1504,IF($B$6="All","<>",$B$6),'RAW DATA'!$D$5:$D$1504,IF($B$7="All","<>",$B$7),'RAW DATA'!$E$5:$E$1504,IF($B$8="All","<>",$B$8),'RAW DATA'!$F$5:$F$1504,IF($B$9="All","<>",$B$9),'RAW DATA'!$A$5:$A$1504,">="&$F$5,'RAW DATA'!$A$5:$A$1504,"<="&$F$6,'RAW DATA'!$G$5:$G$1504,J18) -> 47914620 | L18: =SUMIFS('RAW DATA'!$M$5:$M$1504,'RAW DATA'!$B$5:$B$1504,$B$5,'RAW DATA'!$C$5:$C$1504,IF($B$6="All","<>",$B$6),'RAW DATA'!$D$5:$D$1504,IF($B$7="All","<>",$B$7),'RAW DATA'!$E$5:$E$1504,IF($B$8="All","<>",$B$8),'RAW DATA'!$F$5:$F$1504,IF($B$9="All","<>",$B$9),'RAW DATA'!$A$5:$A$1504,">="&$F$5,'RAW DATA'!$A$5:$A$1504,"<="&$F$6,'RAW DATA'!$G$5:$G$1504,J18) -> 13409245 | M18: =SUMIFS('RAW DATA'!$J$5:$J$1504,'RAW DATA'!$B$5:$B$1504,$B$5,'RAW DATA'!$C$5:$C$1504,IF($B$6="All","<>",$B$6),'RAW DATA'!$D$5:$D$1504,IF($B$7="All","<>",$B$7),'RAW DATA'!$E$5:$E$1504,IF($B$8="All","<>",$B$8),'RAW DATA'!$F$5:$F$1504,IF($B$9="All","<>",$B$9),'RAW DATA'!$A$5:$A$1504,">="&$F$5,'RAW DATA'!$A$5:$A$1504,"<="&$F$6,'RAW DATA'!$G$5:$G$1504,J18) -> 647
A19: Category | B19: =_xlfn.XLOOKUP(I14,'MASTER DATA'!$A$5:$A$20,'MASTER DATA'!$B$5:$B$20,"Not Found") -> Electronics | D19: Manager | E19: =IF($B$8="All","—",INDEX('MASTER DATA'!$D$24:$D$47,MATCH($B$8,'MASTER DATA'!$A$24:$A$47,0))) -> — | G19: Month | H19: Sales | J19: Monitor 27 | K19: =SUMIFS('RAW DATA'!$K$5:$K$1504,'RAW DATA'!$B$5:$B$1504,$B$5,'RAW DATA'!$C$5:$C$1504,IF($B$6="All","<>",$B$6),'RAW DATA'!$D$5:$D$1504,IF($B$7="All","<>",$B$7),'RAW DATA'!$E$5:$E$1504,IF($B$8="All","<>",$B$8),'RAW DATA'!$F$5:$F$1504,IF($B$9="All","<>",$B$9),'RAW DATA'!$A$5:$A$1504,">="&$F$5,'RAW DATA'!$A$5:$A$1504,"<="&$F$6,'RAW DATA'!$G$5:$G$1504,J19) -> 15246420 | L19: =SUMIFS('RAW DATA'!$M$5:$M$1504,'RAW DATA'!$B$5:$B$1504,$B$5,'RAW DATA'!$C$5:$C$1504,IF($B$6="All","<>",$B$6),'RAW DATA'!$D$5:$D$1504,IF($B$7="All","<>",$B$7),'RAW DATA'!$E$5:$E$1504,IF($B$8="All","<>",$B$8),'RAW DATA'!$F$5:$F$1504,IF($B$9="All","<>",$B$9),'RAW DATA'!$A$5:$A$1504,">="&$F$5,'RAW DATA'!$A$5:$A$1504,"<="&$F$6,'RAW DATA'!$G$5:$G$1504,J19) -> 4289835 | M19: =SUMIFS('RAW DATA'!$J$5:$J$1504,'RAW DATA'!$B$5:$B$1504,$B$5,'RAW DATA'!$C$5:$C$1504,IF($B$6="All","<>",$B$6),'RAW DATA'!$D$5:$D$1504,IF($B$7="All","<>",$B$7),'RAW DATA'!$E$5:$E$1504,IF($B$8="All","<>",$B$8),'RAW DATA'!$F$5:$F$1504,IF($B$9="All","<>",$B$9),'RAW DATA'!$A$5:$A$1504,">="&$F$5,'RAW DATA'!$A$5:$A$1504,"<="&$F$6,'RAW DATA'!$G$5:$G$1504,J19) -> 764
A20: Unit Price | B20: =_xlfn.XLOOKUP(I14,'MASTER DATA'!$A$5:$A$20,'MASTER DATA'!$C$5:$C$20,0) -> 78000 | D20: Region | E20: =IF($B$8="All","All",INDEX('MASTER DATA'!$C$24:$C$47,MATCH($B$8,'MASTER DATA'!$A$24:$A$47,0))) -> All | G20: Jan | H20: =SUMIFS('RAW DATA'!$K$5:$K$1504,'RAW DATA'!$B$5:$B$1504,$B$5,'RAW DATA'!$C$5:$C$1504,IF($B$6="All","<>",$B$6),'RAW DATA'!$D$5:$D$1504,IF($B$7="All","<>",$B$7),'RAW DATA'!$E$5:$E$1504,IF($B$8="All","<>",$B$8),'RAW DATA'!$F$5:$F$1504,IF($B$9="All","<>",$B$9),'RAW DATA'!$A$5:$A$1504,">="&$F$5,'RAW DATA'!$A$5:$A$1504,"<="&$F$6,'RAW DATA'!$A$5:$A$1504,">="&DATE(2026,1,1),'RAW DATA'!$A$5:$A$1504,"<"&EDATE(DATE(2026,1,1),1)) -> 30378474 | J20: Tablet X | K20: =SUMIFS('RAW DATA'!$K$5:$K$1504,'RAW DATA'!$B$5:$B$1504,$B$5,'RAW DATA'!$C$5:$C$1504,IF($B$6="All","<>",$B$6),'RAW DATA'!$D$5:$D$1504,IF($B$7="All","<>",$B$7),'RAW DATA'!$E$5:$E$1504,IF($B$8="All","<>",$B$8),'RAW DATA'!$F$5:$F$1504,IF($B$9="All","<>",$B$9),'RAW DATA'!$A$5:$A$1504,">="&$F$5,'RAW DATA'!$A$5:$A$1504,"<="&$F$6,'RAW DATA'!$G$5:$G$1504,J20) -> 25294170 | L20: =SUMIFS('RAW DATA'!$M$5:$M$1504,'RAW DATA'!$B$5:$B$1504,$B$5,'RAW DATA'!$C$5:$C$1504,IF($B$6="All","<>",$B$6),'RAW DATA'!$D$5:$D$1504,IF($B$7="All","<>",$B$7),'RAW DATA'!$E$5:$E$1504,IF($B$8="All","<>",$B$8),'RAW DATA'!$F$5:$F$1504,IF($B$9="All","<>",$B$9),'RAW DATA'!$A$5:$A$1504,">="&$F$5,'RAW DATA'!$A$5:$A$1504,"<="&$F$6,'RAW DATA'!$G$5:$G$1504,J20) -> 7086714.4 | M20: =SUMIFS('RAW DATA'!$J$5:$J$1504,'RAW DATA'!$B$5:$B$1504,$B$5,'RAW DATA'!$C$5:$C$1504,IF($B$6="All","<>",$B$6),'RAW DATA'!$D$5:$D$1504,IF($B$7="All","<>",$B$7),'RAW DATA'!$E$5:$E$1504,IF($B$8="All","<>",$B$8),'RAW DATA'!$F$5:$F$1504,IF($B$9="All","<>",$B$9),'RAW DATA'!$A$5:$A$1504,">="&$F$5,'RAW DATA'!$A$5:$A$1504,"<="&$F$6,'RAW DATA'!$G$5:$G$1504,J20) -> 808
A21: Supplier | B21: =_xlfn.XLOOKUP(I14,'MASTER DATA'!$A$5:$A$20,'MASTER DATA'!$D$5:$D$20,"Not Found") -> SUP04 | G21: Feb | H21: =SUMIFS('RAW DATA'!$K$5:$K$1504,'RAW DATA'!$B$5:$B$1504,$B$5,'RAW DATA'!$C$5:$C$1504,IF($B$6="All","<>",$B$6),'RAW DATA'!$D$5:$D$1504,IF($B$7="All","<>",$B$7),'RAW DATA'!$E$5:$E$1504,IF($B$8="All","<>",$B$8),'RAW DATA'!$F$5:$F$1504,IF($B$9="All","<>",$B$9),'RAW DATA'!$A$5:$A$1504,">="&$F$5,'RAW DATA'!$A$5:$A$1504,"<="&$F$6,'RAW DATA'!$A$5:$A$1504,">="&DATE(2026,2,1),'RAW DATA'!$A$5:$A$1504,"<"&EDATE(DATE(2026,2,1),1)) -> 22027539 | J21: Printer Pro | K21: =SUMIFS('RAW DATA'!$K$5:$K$1504,'RAW DATA'!$B$5:$B$1504,$B$5,'RAW DATA'!$C$5:$C$1504,IF($B$6="All","<>",$B$6),'RAW DATA'!$D$5:$D$1504,IF($B$7="All","<>",$B$7),'RAW DATA'!$E$5:$E$1504,IF($B$8="All","<>",$B$8),'RAW DATA'!$F$5:$F$1504,IF($B$9="All","<>",$B$9),'RAW DATA'!$A$5:$A$1504,">="&$F$5,'RAW DATA'!$A$5:$A$1504,"<="&$F$6,'RAW DATA'!$G$5:$G$1504,J21) -> 11813945 | L21: =SUMIFS('RAW DATA'!$M$5:$M$1504,'RAW DATA'!$B$5:$B$1504,$B$5,'RAW DATA'!$C$5:$C$1504,IF($B$6="All","<>",$B$6),'RAW DATA'!$D$5:$D$1504,IF($B$7="All","<>",$B$7),'RAW DATA'!$E$5:$E$1504,IF($B$8="All","<>",$B$8),'RAW DATA'!$F$5:$F$1504,IF($B$9="All","<>",$B$9),'RAW DATA'!$A$5:$A$1504,">="&$F$5,'RAW DATA'!$A$5:$A$1504,"<="&$F$6,'RAW DATA'!$G$5:$G$1504,J21) -> 3357729 | M21: =SUMIFS('RAW DATA'!$J$5:$J$1504,'RAW DATA'!$B$5:$B$1504,$B$5,'RAW DATA'!$C$5:$C$1504,IF($B$6="All","<>",$B$6),'RAW DATA'!$D$5:$D$1504,IF($B$7="All","<>",$B$7),'RAW DATA'!$E$5:$E$1504,IF($B$8="All","<>",$B$8),'RAW DATA'!$F$5:$F$1504,IF($B$9="All","<>",$B$9),'RAW DATA'!$A$5:$A$1504,">="&$F$5,'RAW DATA'!$A$5:$A$1504,"<="&$F$6,'RAW DATA'!$G$5:$G$1504,J21) -> 799
G22: Mar | H22: =SUMIFS('RAW DATA'!$K$5:$K$1504,'RAW DATA'!$B$5:$B$1504,$B$5,'RAW DATA'!$C$5:$C$1504,IF($B$6="All","<>",$B$6),'RAW DATA'!$D$5:$D$1504,IF($B$7="All","<>",$B$7),'RAW DATA'!$E$5:$E$1504,IF($B$8="All","<>",$B$8),'RAW DATA'!$F$5:$F$1504,IF($B$9="All","<>",$B$9),'RAW DATA'!$A$5:$A$1504,">="&$F$5,'RAW DATA'!$A$5:$A$1504,"<="&$F$6,'RAW DATA'!$A$5:$A$1504,">="&DATE(2026,3,1),'RAW DATA'!$A$5:$A$1504,"<"&EDATE(DATE(2026,3,1),1)) -> 24126996 | J22: Keyboard | K22: =SUMIFS('RAW DATA'!$K$5:$K$1504,'RAW DATA'!$B$5:$B$1504,$B$5,'RAW DATA'!$C$5:$C$1504,IF($B$6="All","<>",$B$6),'RAW DATA'!$D$5:$D$1504,IF($B$7="All","<>",$B$7),'RAW DATA'!$E$5:$E$1504,IF($B$8="All","<>",$B$8),'RAW DATA'!$F$5:$F$1504,IF($B$9="All","<>",$B$9),'RAW DATA'!$A$5:$A$1504,">="&$F$5,'RAW DATA'!$A$5:$A$1504,"<="&$F$6,'RAW DATA'!$G$5:$G$1504,J22) -> 1910464 | L22: =SUMIFS('RAW DATA'!$M$5:$M$1504,'RAW DATA'!$B$5:$B$1504,$B$5,'RAW DATA'!$C$5:$C$1504,IF($B$6="All","<>",$B$6),'RAW DATA'!$D$5:$D$1504,IF($B$7="All","<>",$B$7),'RAW DATA'!$E$5:$E$1504,IF($B$8="All","<>",$B$8),'RAW DATA'!$F$5:$F$1504,IF($B$9="All","<>",$B$9),'RAW DATA'!$A$5:$A$1504,">="&$F$5,'RAW DATA'!$A$5:$A$1504,"<="&$F$6,'RAW DATA'!$G$5:$G$1504,J22) -> 555392.4 | M22: =SUMIFS('RAW DATA'!$J$5:$J$1504,'RAW DATA'!$B$5:$B$1504,$B$5,'RAW DATA'!$C$5:$C$1504,IF($B$6="All","<>",$B$6),'RAW DATA'!$D$5:$D$1504,IF($B$7="All","<>",$B$7),'RAW DATA'!$E$5:$E$1504,IF($B$8="All","<>",$B$8),'RAW DATA'!$F$5:$F$1504,IF($B$9="All","<>",$B$9),'RAW DATA'!$A$5:$A$1504,">="&$F$5,'RAW DATA'!$A$5:$A$1504,"<="&$F$6,'RAW DATA'!$G$5:$G$1504,J22) -> 627
G23: Apr | H23: =SUMIFS('RAW DATA'!$K$5:$K$1504,'RAW DATA'!$B$5:$B$1504,$B$5,'RAW DATA'!$C$5:$C$1504,IF($B$6="All","<>",$B$6),'RAW DATA'!$D$5:$D$1504,IF($B$7="All","<>",$B$7),'RAW DATA'!$E$5:$E$1504,IF($B$8="All","<>",$B$8),'RAW DATA'!$F$5:$F$1504,IF($B$9="All","<>",$B$9),'RAW DATA'!$A$5:$A$1504,">="&$F$5,'RAW DATA'!$A$5:$A$1504,"<="&$F$6,'RAW DATA'!$A$5:$A$1504,">="&DATE(2026,4,1),'RAW DATA'!$A$5:$A$1504,"<"&EDATE(DATE(2026,4,1),1)) -> 24942867 | J23: Headset | K23: =SUMIFS('RAW DATA'!$K$5:$K$1504,'RAW DATA'!$B$5:$B$1504,$B$5,'RAW DATA'!$C$5:$C$1504,IF($B$6="All","<>",$B$6),'RAW DATA'!$D$5:$D$1504,IF($B$7="All","<>",$B$7),'RAW DATA'!$E$5:$E$1504,IF($B$8="All","<>",$B$8),'RAW DATA'!$F$5:$F$1504,IF($B$9="All","<>",$B$9),'RAW DATA'!$A$5:$A$1504,">="&$F$5,'RAW DATA'!$A$5:$A$1504,"<="&$F$6,'RAW DATA'!$G$5:$G$1504,J23) -> 3602544 | L23: =SUMIFS('RAW DATA'!$M$5:$M$1504,'RAW DATA'!$B$5:$B$1504,$B$5,'RAW DATA'!$C$5:$C$1504,IF($B$6="All","<>",$B$6),'RAW DATA'!$D$5:$D$1504,IF($B$7="All","<>",$B$7),'RAW DATA'!$E$5:$E$1504,IF($B$8="All","<>",$B$8),'RAW DATA'!$F$5:$F$1504,IF($B$9="All","<>",$B$9),'RAW DATA'!$A$5:$A$1504,">="&$F$5,'RAW DATA'!$A$5:$A$1504,"<="&$F$6,'RAW DATA'!$G$5:$G$1504,J23) -> 1034301.2 | M23: =SUMIFS('RAW DATA'!$J$5:$J$1504,'RAW DATA'!$B$5:$B$1504,$B$5,'RAW DATA'!$C$5:$C$1504,IF($B$6="All","<>",$B$6),'RAW DATA'!$D$5:$D$1504,IF($B$7="All","<>",$B$7),'RAW DATA'!$E$5:$E$1504,IF($B$8="All","<>",$B$8),'RAW DATA'!$F$5:$F$1504,IF($B$9="All","<>",$B$9),'RAW DATA'!$A$5:$A$1504,">="&$F$5,'RAW DATA'!$A$5:$A$1504,"<="&$F$6,'RAW DATA'!$G$5:$G$1504,J23) -> 787
G24: May | H24: =SUMIFS('RAW DATA'!$K$5:$K$1504,'RAW DATA'!$B$5:$B$1504,$B$5,'RAW DATA'!$C$5:$C$1504,IF($B$6="All","<>",$B$6),'RAW DATA'!$D$5:$D$1504,IF($B$7="All","<>",$B$7),'RAW DATA'!$E$5:$E$1504,IF($B$8="All","<>",$B$8),'RAW DATA'!$F$5:$F$1504,IF($B$9="All","<>",$B$9),'RAW DATA'!$A$5:$A$1504,">="&$F$5,'RAW DATA'!$A$5:$A$1504,"<="&$F$6,'RAW DATA'!$A$5:$A$1504,">="&DATE(2026,5,1),'RAW DATA'!$A$5:$A$1504,"<"&EDATE(DATE(2026,5,1),1)) -> 21829041 | J24: Mouse | K24: =SUMIFS('RAW DATA'!$K$5:$K$1504,'RAW DATA'!$B$5:$B$1504,$B$5,'RAW DATA'!$C$5:$C$1504,IF($B$6="All","<>",$B$6),'RAW DATA'!$D$5:$D$1504,IF($B$7="All","<>",$B$7),'RAW DATA'!$E$5:$E$1504,IF($B$8="All","<>",$B$8),'RAW DATA'!$F$5:$F$1504,IF($B$9="All","<>",$B$9),'RAW DATA'!$A$5:$A$1504,">="&$F$5,'RAW DATA'!$A$5:$A$1504,"<="&$F$6,'RAW DATA'!$G$5:$G$1504,J24) -> 763740 | L24: =SUMIFS('RAW DATA'!$M$5:$M$1504,'RAW DATA'!$B$5:$B$1504,$B$5,'RAW DATA'!$C$5:$C$1504,IF($B$6="All","<>",$B$6),'RAW DATA'!$D$5:$D$1504,IF($B$7="All","<>",$B$7),'RAW DATA'!$E$5:$E$1504,IF($B$8="All","<>",$B$8),'RAW DATA'!$F$5:$F$1504,IF($B$9="All","<>",$B$9),'RAW DATA'!$A$5:$A$1504,">="&$F$5,'RAW DATA'!$A$5:$A$1504,"<="&$F$6,'RAW DATA'!$G$5:$G$1504,J24) -> 224808.69 | M24: =SUMIFS('RAW DATA'!$J$5:$J$1504,'RAW DATA'!$B$5:$B$1504,$B$5,'RAW DATA'!$C$5:$C$1504,IF($B$6="All","<>",$B$6),'RAW DATA'!$D$5:$D$1504,IF($B$7="All","<>",$B$7),'RAW DATA'!$E$5:$E$1504,IF($B$8="All","<>",$B$8),'RAW DATA'!$F$5:$F$1504,IF($B$9="All","<>",$B$9),'RAW DATA'!$A$5:$A$1504,">="&$F$5,'RAW DATA'!$A$5:$A$1504,"<="&$F$6,'RAW DATA'!$G$5:$G$1504,J24) -> 445
G25: Jun | H25: =SUMIFS('RAW DATA'!$K$5:$K$1504,'RAW DATA'!$B$5:$B$1504,$B$5,'RAW DATA'!$C$5:$C$1504,IF($B$6="All","<>",$B$6),'RAW DATA'!$D$5:$D$1504,IF($B$7="All","<>",$B$7),'RAW DATA'!$E$5:$E$1504,IF($B$8="All","<>",$B$8),'RAW DATA'!$F$5:$F$1504,IF($B$9="All","<>",$B$9),'RAW DATA'!$A$5:$A$1504,">="&$F$5,'RAW DATA'!$A$5:$A$1504,"<="&$F$6,'RAW DATA'!$A$5:$A$1504,">="&DATE(2026,6,1),'RAW DATA'!$A$5:$A$1504,"<"&EDATE(DATE(2026,6,1),1)) -> 25875630 | J25: Webcam | K25: =SUMIFS('RAW DATA'!$K$5:$K$1504,'RAW DATA'!$B$5:$B$1504,$B$5,'RAW DATA'!$C$5:$C$1504,IF($B$6="All","<>",$B$6),'RAW DATA'!$D$5:$D$1504,IF($B$7="All","<>",$B$7),'RAW DATA'!$E$5:$E$1504,IF($B$8="All","<>",$B$8),'RAW DATA'!$F$5:$F$1504,IF($B$9="All","<>",$B$9),'RAW DATA'!$A$5:$A$1504,">="&$F$5,'RAW DATA'!$A$5:$A$1504,"<="&$F$6,'RAW DATA'!$G$5:$G$1504,J25) -> 3141516 | L25: =SUMIFS('RAW DATA'!$M$5:$M$1504,'RAW DATA'!$B$5:$B$1504,$B$5,'RAW DATA'!$C$5:$C$1504,IF($B$6="All","<>",$B$6),'RAW DATA'!$D$5:$D$1504,IF($B$7="All","<>",$B$7),'RAW DATA'!$E$5:$E$1504,IF($B$8="All","<>",$B$8),'RAW DATA'!$F$5:$F$1504,IF($B$9="All","<>",$B$9),'RAW DATA'!$A$5:$A$1504,">="&$F$5,'RAW DATA'!$A$5:$A$1504,"<="&$F$6,'RAW DATA'!$G$5:$G$1504,J25) -> 841245.27 | M25: =SUMIFS('RAW DATA'!$J$5:$J$1504,'RAW DATA'!$B$5:$B$1504,$B$5,'RAW DATA'!$C$5:$C$1504,IF($B$6="All","<>",$B$6),'RAW DATA'!$D$5:$D$1504,IF($B$7="All","<>",$B$7),'RAW DATA'!$E$5:$E$1504,IF($B$8="All","<>",$B$8),'RAW DATA'!$F$5:$F$1504,IF($B$9="All","<>",$B$9),'RAW DATA'!$A$5:$A$1504,">="&$F$5,'RAW DATA'!$A$5:$A$1504,"<="&$F$6,'RAW DATA'!$G$5:$G$1504,J25) -> 784
G26: Jul | H26: =SUMIFS('RAW DATA'!$K$5:$K$1504,'RAW DATA'!$B$5:$B$1504,$B$5,'RAW DATA'!$C$5:$C$1504,IF($B$6="All","<>",$B$6),'RAW DATA'!$D$5:$D$1504,IF($B$7="All","<>",$B$7),'RAW DATA'!$E$5:$E$1504,IF($B$8="All","<>",$B$8),'RAW DATA'!$F$5:$F$1504,IF($B$9="All","<>",$B$9),'RAW DATA'!$A$5:$A$1504,">="&$F$5,'RAW DATA'!$A$5:$A$1504,"<="&$F$6,'RAW DATA'!$A$5:$A$1504,">="&DATE(2026,7,1),'RAW DATA'!$A$5:$A$1504,"<"&EDATE(DATE(2026,7,1),1)) -> 24177615 | J26: Office Chair | K26: =SUMIFS('RAW DATA'!$K$5:$K$1504,'RAW DATA'!$B$5:$B$1504,$B$5,'RAW DATA'!$C$5:$C$1504,IF($B$6="All","<>",$B$6),'RAW DATA'!$D$5:$D$1504,IF($B$7="All","<>",$B$7),'RAW DATA'!$E$5:$E$1504,IF($B$8="All","<>",$B$8),'RAW DATA'!$F$5:$F$1504,IF($B$9="All","<>",$B$9),'RAW DATA'!$A$5:$A$1504,">="&$F$5,'RAW DATA'!$A$5:$A$1504,"<="&$F$6,'RAW DATA'!$G$5:$G$1504,J26) -> 8244125 | L26: =SUMIFS('RAW DATA'!$M$5:$M$1504,'RAW DATA'!$B$5:$B$1504,$B$5,'RAW DATA'!$C$5:$C$1504,IF($B$6="All","<>",$B$6),'RAW DATA'!$D$5:$D$1504,IF($B$7="All","<>",$B$7),'RAW DATA'!$E$5:$E$1504,IF($B$8="All","<>",$B$8),'RAW DATA'!$F$5:$F$1504,IF($B$9="All","<>",$B$9),'RAW DATA'!$A$5:$A$1504,">="&$F$5,'RAW DATA'!$A$5:$A$1504,"<="&$F$6,'RAW DATA'!$G$5:$G$1504,J26) -> 2284381.7 | M26: =SUMIFS('RAW DATA'!$J$5:$J$1504,'RAW DATA'!$B$5:$B$1504,$B$5,'RAW DATA'!$C$5:$C$1504,IF($B$6="All","<>",$B$6),'RAW DATA'!$D$5:$D$1504,IF($B$7="All","<>",$B$7),'RAW DATA'!$E$5:$E$1504,IF($B$8="All","<>",$B$8),'RAW DATA'!$F$5:$F$1504,IF($B$9="All","<>",$B$9),'RAW DATA'!$A$5:$A$1504,">="&$F$5,'RAW DATA'!$A$5:$A$1504,"<="&$F$6,'RAW DATA'!$G$5:$G$1504,J26) -> 690
G27: Aug | H27: =SUMIFS('RAW DATA'!$K$5:$K$1504,'RAW DATA'!$B$5:$B$1504,$B$5,'RAW DATA'!$C$5:$C$1504,IF($B$6="All","<>",$B$6),'RAW DATA'!$D$5:$D$1504,IF($B$7="All","<>",$B$7),'RAW DATA'!$E$5:$E$1504,IF($B$8="All","<>",$B$8),'RAW DATA'!$F$5:$F$1504,IF($B$9="All","<>",$B$9),'RAW DATA'!$A$5:$A$1504,">="&$F$5,'RAW DATA'!$A$5:$A$1504,"<="&$F$6,'RAW DATA'!$A$5:$A$1504,">="&DATE(2026,8,1),'RAW DATA'!$A$5:$A$1504,"<"&EDATE(DATE(2026,8,1),1)) -> 22591192 | J27: Standing Desk | K27: =SUMIFS('RAW DATA'!$K$5:$K$1504,'RAW DATA'!$B$5:$B$1504,$B$5,'RAW DATA'!$C$5:$C$1504,IF($B$6="All","<>",$B$6),'RAW DATA'!$D$5:$D$1504,IF($B$7="All","<>",$B$7),'RAW DATA'!$E$5:$E$1504,IF($B$8="All","<>",$B$8),'RAW DATA'!$F$5:$F$1504,IF($B$9="All","<>",$B$9),'RAW DATA'!$A$5:$A$1504,">="&$F$5,'RAW DATA'!$A$5:$A$1504,"<="&$F$6,'RAW DATA'!$G$5:$G$1504,J27) -> 14592285 | L27: =SUMIFS('RAW DATA'!$M$5:$M$1504,'RAW DATA'!$B$5:$B$1504,$B$5,'RAW DATA'!$C$5:$C$1504,IF($B$6="All","<>",$B$6),'RAW DATA'!$D$5:$D$1504,IF($B$7="All","<>",$B$7),'RAW DATA'!$E$5:$E$1504,IF($B$8="All","<>",$B$8),'RAW DATA'!$F$5:$F$1504,IF($B$9="All","<>",$B$9),'RAW DATA'!$A$5:$A$1504,">="&$F$5,'RAW DATA'!$A$5:$A$1504,"<="&$F$6,'RAW DATA'!$G$5:$G$1504,J27) -> 3679411.3 | M27: =SUMIFS('RAW DATA'!$J$5:$J$1504,'RAW DATA'!$B$5:$B$1504,$B$5,'RAW DATA'!$C$5:$C$1504,IF($B$6="All","<>",$B$6),'RAW DATA'!$D$5:$D$1504,IF($B$7="All","<>",$B$7),'RAW DATA'!$E$5:$E$1504,IF($B$8="All","<>",$B$8),'RAW DATA'!$F$5:$F$1504,IF($B$9="All","<>",$B$9),'RAW DATA'!$A$5:$A$1504,">="&$F$5,'RAW DATA'!$A$5:$A$1504,"<="&$F$6,'RAW DATA'!$G$5:$G$1504,J27) -> 539
J28: Meeting Table | K28: =SUMIFS('RAW DATA'!$K$5:$K$1504,'RAW DATA'!$B$5:$B$1504,$B$5,'RAW DATA'!$C$5:$C$1504,IF($B$6="All","<>",$B$6),'RAW DATA'!$D$5:$D$1504,IF($B$7="All","<>",$B$7),'RAW DATA'!$E$5:$E$1504,IF($B$8="All","<>",$B$8),'RAW DATA'!$F$5:$F$1504,IF($B$9="All","<>",$B$9),'RAW DATA'!$A$5:$A$1504,">="&$F$5,'RAW DATA'!$A$5:$A$1504,"<="&$F$6,'RAW DATA'!$G$5:$G$1504,J28) -> 22123800 | L28: =SUMIFS('RAW DATA'!$M$5:$M$1504,'RAW DATA'!$B$5:$B$1504,$B$5,'RAW DATA'!$C$5:$C$1504,IF($B$6="All","<>",$B$6),'RAW DATA'!$D$5:$D$1504,IF($B$7="All","<>",$B$7),'RAW DATA'!$E$5:$E$1504,IF($B$8="All","<>",$B$8),'RAW DATA'!$F$5:$F$1504,IF($B$9="All","<>",$B$9),'RAW DATA'!$A$5:$A$1504,">="&$F$5,'RAW DATA'!$A$5:$A$1504,"<="&$F$6,'RAW DATA'!$G$5:$G$1504,J28) -> 6117911 | M28: =SUMIFS('RAW DATA'!$J$5:$J$1504,'RAW DATA'!$B$5:$B$1504,$B$5,'RAW DATA'!$C$5:$C$1504,IF($B$6="All","<>",$B$6),'RAW DATA'!$D$5:$D$1504,IF($B$7="All","<>",$B$7),'RAW DATA'!$E$5:$E$1504,IF($B$8="All","<>",$B$8),'RAW DATA'!$F$5:$F$1504,IF($B$9="All","<>",$B$9),'RAW DATA'!$A$5:$A$1504,">="&$F$5,'RAW DATA'!$A$5:$A$1504,"<="&$F$6,'RAW DATA'!$G$5:$G$1504,J28) -> 644
J29: Filing Cabinet | K29: =SUMIFS('RAW DATA'!$K$5:$K$1504,'RAW DATA'!$B$5:$B$1504,$B$5,'RAW DATA'!$C$5:$C$1504,IF($B$6="All","<>",$B$6),'RAW DATA'!$D$5:$D$1504,IF($B$7="All","<>",$B$7),'RAW DATA'!$E$5:$E$1504,IF($B$8="All","<>",$B$8),'RAW DATA'!$F$5:$F$1504,IF($B$9="All","<>",$B$9),'RAW DATA'!$A$5:$A$1504,">="&$F$5,'RAW DATA'!$A$5:$A$1504,"<="&$F$6,'RAW DATA'!$G$5:$G$1504,J29) -> 9107885 | L29: =SUMIFS('RAW DATA'!$M$5:$M$1504,'RAW DATA'!$B$5:$B$1504,$B$5,'RAW DATA'!$C$5:$C$1504,IF($B$6="All","<>",$B$6),'RAW DATA'!$D$5:$D$1504,IF($B$7="All","<>",$B$7),'RAW DATA'!$E$5:$E$1504,IF($B$8="All","<>",$B$8),'RAW DATA'!$F$5:$F$1504,IF($B$9="All","<>",$B$9),'RAW DATA'!$A$5:$A$1504,">="&$F$5,'RAW DATA'!$A$5:$A$1504,"<="&$F$6,'RAW DATA'!$G$5:$G$1504,J29) -> 2646367.1 | M29: =SUMIFS('RAW DATA'!$J$5:$J$1504,'RAW DATA'!$B$5:$B$1504,$B$5,'RAW DATA'!$C$5:$C$1504,IF($B$6="All","<>",$B$6),'RAW DATA'!$D$5:$D$1504,IF($B$7="All","<>",$B$7),'RAW DATA'!$E$5:$E$1504,IF($B$8="All","<>",$B$8),'RAW DATA'!$F$5:$F$1504,IF($B$9="All","<>",$B$9),'RAW DATA'!$A$5:$A$1504,">="&$F$5,'RAW DATA'!$A$5:$A$1504,"<="&$F$6,'RAW DATA'!$G$5:$G$1504,J29) -> 657
J30: Air Purifier | K30: =SUMIFS('RAW DATA'!$K$5:$K$1504,'RAW DATA'!$B$5:$B$1504,$B$5,'RAW DATA'!$C$5:$C$1504,IF($B$6="All","<>",$B$6),'RAW DATA'!$D$5:$D$1504,IF($B$7="All","<>",$B$7),'RAW DATA'!$E$5:$E$1504,IF($B$8="All","<>",$B$8),'RAW DATA'!$F$5:$F$1504,IF($B$9="All","<>",$B$9),'RAW DATA'!$A$5:$A$1504,">="&$F$5,'RAW DATA'!$A$5:$A$1504,"<="&$F$6,'RAW DATA'!$G$5:$G$1504,J30) -> 10771920 | L30: =SUMIFS('RAW DATA'!$M$5:$M$1504,'RAW DATA'!$B$5:$B$1504,$B$5,'RAW DATA'!$C$5:$C$1504,IF($B$6="All","<>",$B$6),'RAW DATA'!$D$5:$D$1504,IF($B$7="All","<>",$B$7),'RAW DATA'!$E$5:$E$1504,IF($B$8="All","<>",$B$8),'RAW DATA'!$F$5:$F$1504,IF($B$9="All","<>",$B$9),'RAW DATA'!$A$5:$A$1504,">="&$F$5,'RAW DATA'!$A$5:$A$1504,"<="&$F$6,'RAW DATA'!$G$5:$G$1504,J30) -> 3011457.1 | M30: =SUMIFS('RAW DATA'!$J$5:$J$1504,'RAW DATA'!$B$5:$B$1504,$B$5,'RAW DATA'!$C$5:$C$1504,IF($B$6="All","<>",$B$6),'RAW DATA'!$D$5:$D$1504,IF($B$7="All","<>",$B$7),'RAW DATA'!$E$5:$E$1504,IF($B$8="All","<>",$B$8),'RAW DATA'!$F$5:$F$1504,IF($B$9="All","<>",$B$9),'RAW DATA'!$A$5:$A$1504,">="&$F$5,'RAW DATA'!$A$5:$A$1504,"<="&$F$6,'RAW DATA'!$G$5:$G$1504,J30) -> 628
J31: Coffee Maker | K31: =SUMIFS('RAW DATA'!$K$5:$K$1504,'RAW DATA'!$B$5:$B$1504,$B$5,'RAW DATA'!$C$5:$C$1504,IF($B$6="All","<>",$B$6),'RAW DATA'!$D$5:$D$1504,IF($B$7="All","<>",$B$7),'RAW DATA'!$E$5:$E$1504,IF($B$8="All","<>",$B$8),'RAW DATA'!$F$5:$F$1504,IF($B$9="All","<>",$B$9),'RAW DATA'!$A$5:$A$1504,">="&$F$5,'RAW DATA'!$A$5:$A$1504,"<="&$F$6,'RAW DATA'!$G$5:$G$1504,J31) -> 4655560 | L31: =SUMIFS('RAW DATA'!$M$5:$M$1504,'RAW DATA'!$B$5:$B$1504,$B$5,'RAW DATA'!$C$5:$C$1504,IF($B$6="All","<>",$B$6),'RAW DATA'!$D$5:$D$1504,IF($B$7="All","<>",$B$7),'RAW DATA'!$E$5:$E$1504,IF($B$8="All","<>",$B$8),'RAW DATA'!$F$5:$F$1504,IF($B$9="All","<>",$B$9),'RAW DATA'!$A$5:$A$1504,">="&$F$5,'RAW DATA'!$A$5:$A$1504,"<="&$F$6,'RAW DATA'!$G$5:$G$1504,J31) -> 1325301.5 | M31: =SUMIFS('RAW DATA'!$J$5:$J$1504,'RAW DATA'!$B$5:$B$1504,$B$5,'RAW DATA'!$C$5:$C$1504,IF($B$6="All","<>",$B$6),'RAW DATA'!$D$5:$D$1504,IF($B$7="All","<>",$B$7),'RAW DATA'!$E$5:$E$1504,IF($B$8="All","<>",$B$8),'RAW DATA'!$F$5:$F$1504,IF($B$9="All","<>",$B$9),'RAW DATA'!$A$5:$A$1504,">="&$F$5,'RAW DATA'!$A$5:$A$1504,"<="&$F$6,'RAW DATA'!$G$5:$G$1504,J31) -> 756
J32: Microwave | K32: =SUMIFS('RAW DATA'!$K$5:$K$1504,'RAW DATA'!$B$5:$B$1504,$B$5,'RAW DATA'!$C$5:$C$1504,IF($B$6="All","<>",$B$6),'RAW DATA'!$D$5:$D$1504,IF($B$7="All","<>",$B$7),'RAW DATA'!$E$5:$E$1504,IF($B$8="All","<>",$B$8),'RAW DATA'!$F$5:$F$1504,IF($B$9="All","<>",$B$9),'RAW DATA'!$A$5:$A$1504,">="&$F$5,'RAW DATA'!$A$5:$A$1504,"<="&$F$6,'RAW DATA'!$G$5:$G$1504,J32) -> 9655125 | L32: =SUMIFS('RAW DATA'!$M$5:$M$1504,'RAW DATA'!$B$5:$B$1504,$B$5,'RAW DATA'!$C$5:$C$1504,IF($B$6="All","<>",$B$6),'RAW DATA'!$D$5:$D$1504,IF($B$7="All","<>",$B$7),'RAW DATA'!$E$5:$E$1504,IF($B$8="All","<>",$B$8),'RAW DATA'!$F$5:$F$1504,IF($B$9="All","<>",$B$9),'RAW DATA'!$A$5:$A$1504,">="&$F$5,'RAW DATA'!$A$5:$A$1504,"<="&$F$6,'RAW DATA'!$G$5:$G$1504,J32) -> 2673626.8 | M32: =SUMIFS('RAW DATA'!$J$5:$J$1504,'RAW DATA'!$B$5:$B$1504,$B$5,'RAW DATA'!$C$5:$C$1504,IF($B$6="All","<>",$B$6),'RAW DATA'!$D$5:$D$1504,IF($B$7="All","<>",$B$7),'RAW DATA'!$E$5:$E$1504,IF($B$8="All","<>",$B$8),'RAW DATA'!$F$5:$F$1504,IF($B$9="All","<>",$B$9),'RAW DATA'!$A$5:$A$1504,">="&$F$5,'RAW DATA'!$A$5:$A$1504,"<="&$F$6,'RAW DATA'!$G$5:$G$1504,J32) -> 819
J33: Vacuum Cleaner | K33: =SUMIFS('RAW DATA'!$K$5:$K$1504,'RAW DATA'!$B$5:$B$1504,$B$5,'RAW DATA'!$C$5:$C$1504,IF($B$6="All","<>",$B$6),'RAW DATA'!$D$5:$D$1504,IF($B$7="All","<>",$B$7),'RAW DATA'!$E$5:$E$1504,IF($B$8="All","<>",$B$8),'RAW DATA'!$F$5:$F$1504,IF($B$9="All","<>",$B$9),'RAW DATA'!$A$5:$A$1504,">="&$F$5,'RAW DATA'!$A$5:$A$1504,"<="&$F$6,'RAW DATA'!$G$5:$G$1504,J33) -> 7111235 | L33: =SUMIFS('RAW DATA'!$M$5:$M$1504,'RAW DATA'!$B$5:$B$1504,$B$5,'RAW DATA'!$C$5:$C$1504,IF($B$6="All","<>",$B$6),'RAW DATA'!$D$5:$D$1504,IF($B$7="All","<>",$B$7),'RAW DATA'!$E$5:$E$1504,IF($B$8="All","<>",$B$8),'RAW DATA'!$F$5:$F$1504,IF($B$9="All","<>",$B$9),'RAW DATA'!$A$5:$A$1504,">="&$F$5,'RAW DATA'!$A$5:$A$1504,"<="&$F$6,'RAW DATA'!$G$5:$G$1504,J33) -> 2017579.7 | M33: =SUMIFS('RAW DATA'!$J$5:$J$1504,'RAW DATA'!$B$5:$B$1504,$B$5,'RAW DATA'!$C$5:$C$1504,IF($B$6="All","<>",$B$6),'RAW DATA'!$D$5:$D$1504,IF($B$7="All","<>",$B$7),'RAW DATA'!$E$5:$E$1504,IF($B$8="All","<>",$B$8),'RAW DATA'!$F$5:$F$1504,IF($B$9="All","<>",$B$9),'RAW DATA'!$A$5:$A$1504,">="&$F$5,'RAW DATA'!$A$5:$A$1504,"<="&$F$6,'RAW DATA'!$G$5:$G$1504,J33) -> 515
J35: INDIRECT — DYNAMIC SOURCE
J36: Source Sheet | K36: RAW DATA
J37: Reference | K37: {=INDIRECT("'"&K36&"'!A5")} -> 46146
J38: Concept | K38: Text is converted into a real worksheet reference.
J41: Category | K41: Sales | L41: Profit
J42: Electronics | K42: =SUMIFS('RAW DATA'!$K$5:$K$1504,'RAW DATA'!$B$5:$B$1504,$B$5,'RAW DATA'!$C$5:$C$1504,IF($B$6="All","<>",$B$6),'RAW DATA'!$D$5:$D$1504,IF($B$7="All","<>",$B$7),'RAW DATA'!$E$5:$E$1504,IF($B$8="All","<>",$B$8),'RAW DATA'!$F$5:$F$1504,IF($B$9="All","<>",$B$9),'RAW DATA'!$A$5:$A$1504,">="&$F$5,'RAW DATA'!$A$5:$A$1504,"<="&$F$6,'RAW DATA'!$F$5:$F$1504,J42) -> 100269155 | L42: =SUMIFS('RAW DATA'!$M$5:$M$1504,'RAW DATA'!$B$5:$B$1504,$B$5,'RAW DATA'!$C$5:$C$1504,IF($B$6="All","<>",$B$6),'RAW DATA'!$D$5:$D$1504,IF($B$7="All","<>",$B$7),'RAW DATA'!$E$5:$E$1504,IF($B$8="All","<>",$B$8),'RAW DATA'!$F$5:$F$1504,IF($B$9="All","<>",$B$9),'RAW DATA'!$A$5:$A$1504,">="&$F$5,'RAW DATA'!$A$5:$A$1504,"<="&$F$6,'RAW DATA'!$F$5:$F$1504,J42) -> 28143523
J43: Accessories | K43: =SUMIFS('RAW DATA'!$K$5:$K$1504,'RAW DATA'!$B$5:$B$1504,$B$5,'RAW DATA'!$C$5:$C$1504,IF($B$6="All","<>",$B$6),'RAW DATA'!$D$5:$D$1504,IF($B$7="All","<>",$B$7),'RAW DATA'!$E$5:$E$1504,IF($B$8="All","<>",$B$8),'RAW DATA'!$F$5:$F$1504,IF($B$9="All","<>",$B$9),'RAW DATA'!$A$5:$A$1504,">="&$F$5,'RAW DATA'!$A$5:$A$1504,"<="&$F$6,'RAW DATA'!$F$5:$F$1504,J43) -> 9418264 | L43: =SUMIFS('RAW DATA'!$M$5:$M$1504,'RAW DATA'!$B$5:$B$1504,$B$5,'RAW DATA'!$C$5:$C$1504,IF($B$6="All","<>",$B$6),'RAW DATA'!$D$5:$D$1504,IF($B$7="All","<>",$B$7),'RAW DATA'!$E$5:$E$1504,IF($B$8="All","<>",$B$8),'RAW DATA'!$F$5:$F$1504,IF($B$9="All","<>",$B$9),'RAW DATA'!$A$5:$A$1504,">="&$F$5,'RAW DATA'!$A$5:$A$1504,"<="&$F$6,'RAW DATA'!$F$5:$F$1504,J43) -> 2655747.6
J44: Furniture | K44: =SUMIFS('RAW DATA'!$K$5:$K$1504,'RAW DATA'!$B$5:$B$1504,$B$5,'RAW DATA'!$C$5:$C$1504,IF($B$6="All","<>",$B$6),'RAW DATA'!$D$5:$D$1504,IF($B$7="All","<>",$B$7),'RAW DATA'!$E$5:$E$1504,IF($B$8="All","<>",$B$8),'RAW DATA'!$F$5:$F$1504,IF($B$9="All","<>",$B$9),'RAW DATA'!$A$5:$A$1504,">="&$F$5,'RAW DATA'!$A$5:$A$1504,"<="&$F$6,'RAW DATA'!$F$5:$F$1504,J44) -> 54068095 | L44: =SUMIFS('RAW DATA'!$M$5:$M$1504,'RAW DATA'!$B$5:$B$1504,$B$5,'RAW DATA'!$C$5:$C$1504,IF($B$6="All","<>",$B$6),'RAW DATA'!$D$5:$D$1504,IF($B$7="All","<>",$B$7),'RAW DATA'!$E$5:$E$1504,IF($B$8="All","<>",$B$8),'RAW DATA'!$F$5:$F$1504,IF($B$9="All","<>",$B$9),'RAW DATA'!$A$5:$A$1504,">="&$F$5,'RAW DATA'!$A$5:$A$1504,"<="&$F$6,'RAW DATA'!$F$5:$F$1504,J44) -> 14728071
J45: Home | K45: =SUMIFS('RAW DATA'!$K$5:$K$1504,'RAW DATA'!$B$5:$B$1504,$B$5,'RAW DATA'!$C$5:$C$1504,IF($B$6="All","<>",$B$6),'RAW DATA'!$D$5:$D$1504,IF($B$7="All","<>",$B$7),'RAW DATA'!$E$5:$E$1504,IF($B$8="All","<>",$B$8),'RAW DATA'!$F$5:$F$1504,IF($B$9="All","<>",$B$9),'RAW DATA'!$A$5:$A$1504,">="&$F$5,'RAW DATA'!$A$5:$A$1504,"<="&$F$6,'RAW DATA'!$F$5:$F$1504,J45) -> 32193840 | L45: =SUMIFS('RAW DATA'!$M$5:$M$1504,'RAW DATA'!$B$5:$B$1504,$B$5,'RAW DATA'!$C$5:$C$1504,IF($B$6="All","<>",$B$6),'RAW DATA'!$D$5:$D$1504,IF($B$7="All","<>",$B$7),'RAW DATA'!$E$5:$E$1504,IF($B$8="All","<>",$B$8),'RAW DATA'!$F$5:$F$1504,IF($B$9="All","<>",$B$9),'RAW DATA'!$A$5:$A$1504,">="&$F$5,'RAW DATA'!$A$5:$A$1504,"<="&$F$6,'RAW DATA'!$F$5:$F$1504,J45) -> 9027965

Sheet RAW DATA
A1: RAW DATA — SALES TRANSACTIONS
A2: 1,500 records. Dashboard reads this table; learners should not overwrite the source.
A4: Date | B4: Scenario | C4: Region | D4: State | E4: City | F4: Category | G4: Product | H4: Salesperson | I4: Customer ID | J4: Units | K4: Sales | L4: Cost | M4: Profit | N4: Channel | O4: Order Status | P4: Product Key
A5: 46146 | B5: Actual | C5: West | D5: Rajasthan | E5: Udaipur | F5: Accessories | G5: Webcam | H5: Kabir Verma | I5: C05071 | J5: 9 | K5: 37800 | L5: 30593.8 | M5: 7206.2 | N5: Corporate | O5: Closed | P5: =E5&"|"&G5 -> Udaipur|Webcam
A6: 46044 | B6: Budget | C6: West | D6: Gujarat | E6: Ahmedabad | F6: Electronics | G6: Monitor 27 | H6: Aarav Mehta | I6: C05152 | J6: 6 | K6: 119700 | L6: 87454.92 | M6: 32245.08 | N6: Corporate | O6: Returned | P6: =E6&"|"&G6 -> Ahmedabad|Monitor 27
A7: 46264 | B7: Forecast | C7: East | D7: West Bengal | E7: Durgapur | F7: Home | G7: Air Purifier | H7: Aarav Mehta | I7: C05180 | J7: 11 | K7: 198000 | L7: 139555.53 | M7: 58444.47 | N7: Retail Store | O7: Closed | P7: =E7&"|"&G7 -> Durgapur|Air Purifier
A8: 46155 | B8: Actual | C8: North | D8: Haryana | E8: Gurugram | F8: Electronics | G8: Laptop Pro | H8: Ananya Gupta | I8: C05067 | J8: 8 | K8: 574080 | L8: 410710.08 | M8: 163369.92 | N8: Online | O8: Returned | P8: =E8&"|"&G8 -> Gurugram|Laptop Pro
A9: 46216 | B9: Actual | C9: West | D9: Rajasthan | E9: Jaipur | F9: Home | G9: Coffee Maker | H9: Arjun Patel | I9: C05239 | J9: 4 | K9: 24700 | L9: 18150.17 | M9: 6549.83 | N9: Online | O9: Returned | P9: =E9&"|"&G9 -> Jaipur|Coffee Maker
A10: 46071 | B10: Actual | C10: North | D10: Haryana | E10: Gurugram | F10: Electronics | G10: Monitor 27 | H10: Karan Joshi | I10: C05218 | J10: 19 | K10: 379050 | L10: 309954.99 | M10: 69095.01 | N10: Corporate | O10: Closed | P10: =E10&"|"&G10 -> Gurugram|Monitor 27
A11: 46096 | B11: Actual | C11: East | D11: Odisha | E11: Cuttack | F11: Home | G11: Coffee Maker | H11: Riya Singh | I11: C05039 | J11: 10 | K11: 61750 | L11: 42780.36 | M11: 18969.64 | N11: Partner | O11: Pending | P11: =E11&"|"&G11 -> Cuttack|Coffee Maker
A12: 46121 | B12: Actual | C12: North | D12: Haryana | E12: Faridabad | F12: Electronics | G12: Printer Pro | H12: Arjun Patel | I12: C05079 | J12: 15 | K12: 232500 | L12: 172336.81 | M12: 60163.19 | N12: Online | O12: Closed | P12: =E12&"|"&G12 -> Faridabad|Printer Pro
A13: 46186 | B13: Forecast | C13: West | D13: Rajasthan | E13: Jaipur | F13: Electronics | G13: Laptop Pro | H13: Kabir Verma | I13: C05213 | J13: 19 | K13: 1482000 | L13: 1193724.4 | M13: 288275.55 | N13: Partner | O13: Pending | P13: =E13&"|"&G13 -> Jaipur|Laptop Pro
A14: 46052 | B14: Actual | C14: East | D14: Assam | E14: Guwahati | F14: Furniture | G14: Standing Desk | H14: Riya Singh | I14: C05119 | J14: 20 | K14: 541500 | L14: 398137.5 | M14: 143362.5 | N14: Retail Store | O14: Returned | P14: =E14&"|"&G14 -> Guwahati|Standing Desk
A15: 46131 | B15: Actual | C15: West | D15: Maharashtra | E15: Mumbai | F15: Furniture | G15: Office Chair | H15: Ananya Gupta | I15: C05110 | J15: 7 | K15: 87500 | L15: 71246.92 | M15: 16253.08 | N15: Retail Store | O15: Closed | P15: =E15&"|"&G15 -> Mumbai|Office Chair
A16: 46157 | B16: Actual | C16: South | D16: Tamil Nadu | E16: Coimbatore | F16: Accessories | G16: Headset | H16: Kabir Verma | I16: C05207 | J16: 19 | K16: 88464 | L16: 61311.36 | M16: 27152.64 | N16: Partner | O16: Pending | P16: =E16&"|"&G16 -> Coimbatore|Headset
... A1504: 46071 | B1504: Actual | C1504: West | D1504: Maharashtra | E1504: Pune | F1504: Furniture | G1504: Filing Cabinet | H1504: Arjun Patel | I1504: C05085 | J1504: 9 | K1504: 130500 | L1504: 83446.05 | M1504: 47053.95 | N1504: Corporate | O1504: Closed | P1504: =E1504&"|"&G1504 -> Pune|Filing Cabinet

Sheet MASTER DATA
A1: MASTER DATA — LOOKUPS & VALIDATION
A2: Supports XLOOKUP, INDEX+MATCH and INDIRECT-driven dependent dropdowns.
A4: Product | B4: Category | C4: Unit Price | D4: Supplier ID | F4: Validation Lists | N4: States_All | O4: States_North | P4: States_South | Q4: States_West | R4: States_East
A5: Laptop Pro | B5: Electronics | C5: 78000 | D5: SUP04 | F5: All | H5: Actual | J5: All | L5: MTD | N5: Delhi | O5: Delhi | P5: Karnataka | Q5: Maharashtra | R5: West Bengal
A6: Monitor 27 | B6: Electronics | C6: 21000 | D6: SUP04 | F6: North | H6: Budget | J6: Sales | L6: QTD | N6: Haryana | O6: Haryana | P6: Tamil Nadu | Q6: Gujarat | R6: Odisha
A7: Tablet X | B7: Electronics | C7: 33000 | D7: SUP05 | F7: South | H7: Forecast | J7: Profit | L7: YTD | N7: Uttar Pradesh | O7: Uttar Pradesh | P7: Telangana | Q7: Rajasthan | R7: Assam
A8: Printer Pro | B8: Electronics | C8: 15500 | D8: SUP08 | F8: West | J8: Units | N8: Karnataka
A9: Keyboard | B9: Accessories | C9: 3200 | D9: SUP02 | F9: East | N9: Tamil Nadu
A10: Headset | B10: Accessories | C10: 4800 | D10: SUP08 | N10: Telangana
A11: Mouse | B11: Accessories | C11: 1800 | D11: SUP07 | N11: Maharashtra
A12: Webcam | B12: Accessories | C12: 4200 | D12: SUP02 | N12: Gujarat
A13: Office Chair | B13: Furniture | C13: 12500 | D13: SUP06 | N13: Rajasthan
A14: Standing Desk | B14: Furniture | C14: 28500 | D14: SUP06 | N14: West Bengal
A15: Meeting Table | B15: Furniture | C15: 36000 | D15: SUP04 | N15: Odisha
A16: Filing Cabinet | B16: Furniture | C16: 14500 | D16: SUP07 | N16: Assam
A17: Air Purifier | B17: Home | C17: 18000 | D17: SUP05
A18: Coffee Maker | B18: Home | C18: 6500 | D18: SUP03
A19: Microwave | B19: Home | C19: 12500 | D19: SUP05
A20: Vacuum Cleaner | B20: Home | C20: 14500 | D20: SUP07 | N20: Cities_All | O20: Cities_Delhi | P20: Cities_Haryana | Q20: Cities_Uttar_Pradesh | R20: Cities_Karnataka | S20: Cities_Tamil_Nadu | T20: Cities_Telangana | U20: Cities_Maharashtra | V20: Cities_Gujarat | W20: Cities_Rajasthan | X20: Cities_West_Bengal | Y20: Cities_Odisha | Z20: Cities_Assam
N21: Ahmedabad | O21: New Delhi | P21: Gurugram | Q21: Lucknow | R21: Bengaluru | S21: Chennai | T21: Hyderabad | U21: Mumbai | V21: Ahmedabad | W21: Jaipur | X21: Kolkata | Y21: Bhubaneswar | Z21: Guwahati
N22: Bengaluru | O22: Dwarka | P22: Faridabad | Q22: Noida | R22: Mysuru | S22: Coimbatore | T22: Warangal | U22: Pune | V22: Surat | W22: Udaipur | X22: Durgapur | Y22: Cuttack | Z22: Dibrugarh
A23: City | B23: State | C23: Region | D23: City Manager | N23: Bhubaneswar
A24: New Delhi | B24: Delhi | C24: North | D24: A. Mehta | N24: Chennai
A25: Dwarka | B25: Delhi | C25: North | D25: R. Sharma | N25: Coimbatore
A26: Gurugram | B26: Haryana | C26: North | D26: A. Mehta | N26: Cuttack
A27: Faridabad | B27: Haryana | C27: North | D27: P. Iyer | N27: Dibrugarh
A28: Lucknow | B28: Uttar Pradesh | C28: North | D28: R. Sharma | N28: Durgapur
A29: Noida | B29: Uttar Pradesh | C29: North | D29: A. Mehta | N29: Dwarka
A30: Bengaluru | B30: Karnataka | C30: South | D30: R. Sharma | N30: Faridabad
A31: Mysuru | B31: Karnataka | C31: South | D31: P. Iyer | N31: Gurugram
A32: Chennai | B32: Tamil Nadu | C32: South | D32: S. Rao | N32: Guwahati
A33: Coimbatore | B33: Tamil Nadu | C33: South | D33: S. Rao | N33: Hyderabad
A34: Hyderabad | B34: Telangana | C34: South | D34: S. Rao | N34: Jaipur
... A44: Bhubaneswar | B44: Odisha | C44: East | D44: N. Verma | N44: Warangal
A45: Cuttack | B45: Odisha | C45: East | D45: K. Singh
A46: Guwahati | B46: Assam | C46: East | D46: P. Iyer
A47: Dibrugarh | B47: Assam | C47: East | D47: R. Sharma

Sheet FORMULA LAB
A1: FORMULA LAB — FIVE CHAPTERS IN ONE PROJECT
A2: Use this sheet to understand why each function exists in the dashboard.
A4: Chapter | B4: Function | C4: Used for | D4: Formula pattern | E4: Why | F4: Failure / caution
A5: 1 | B5: INDEX + MATCH (Advanced) | C5: Dynamic retrieval after finding the position of a product/city. | D5: {=INDEX(return_range,MATCH(key,lookup_range,0))} -> #NAME? | E5: Separates position from retrieval and avoids hard-coded row numbers. | F5: Exact match and aligned ranges matter.
A6: 2 | B6: XLOOKUP (Advanced) | C6: Return product metadata from the winning product. | D6: {=_xlfn.XLOOKUP(key,lookup_array,return_array,"Not Found")} -> #NAME? | E6: Modern, readable lookup with explicit error handling. | F6: Still needs a sensible unique key.
A7: 3 | B7: OFFSET | C7: Dynamic moving/resizing range logic for trend/chart sources. | D7: {=OFFSET(start,rows,cols,height,width)} -> #NAME? | E7: The range itself can move or resize. | F7: Volatile; avoid indiscriminate use on huge models.
A8: 4 | B8: INDIRECT | C8: Dependent dropdowns and text-driven references. | D8: {=INDIRECT("States_"&SUBSTITUTE(B6," ","_"))} -> #REF! | E8: Turns text into a live Excel reference. | F8: Volatile and fragile if names/sheets change.
A9: 5 | B9: CHOOSE + MATCH + INDEX | C9: One Metric selector drives Sales / Profit / Units. | D9: {=CHOOSE(MATCH(B10,{"Sales","Profit","Units"},0),SalesValue,ProfitValue,UnitsValue)} -> #N/A | E9: Maps user choice to one of several outputs. | F9: Keep option order synchronized.
A12: COMBINATION LOGIC
A13: INDIRECT + Data Validation | B13: Region → State → City dependent dropdowns.
A14: XLOOKUP + INDEX/MATCH | B14: Retrieve metadata after dynamically identifying a product/city.
A15: OFFSET + Chart | B15: Dynamic range concept for a moving analysis window.
A16: CHOOSE + MATCH + INDEX | B16: Metric switcher without separate hard-coded report formulas.
A17: All five | B17: User input → dynamic reference → lookup → metric → KPI → chart.
A20: ARCHITECTURE RULE
A21: Advanced does not mean automatically better. Use the function because the reference, range, selection or output must change dynamically. For very large models, prefer non-volatile alternatives where practical.

Sheet PRACTICE
A1: PRACTICE — REBUILD THE DYNAMIC DASHBOARD
A2: Attempt these tasks using RAW DATA and MASTER DATA before studying the dashboard formulas.
A4: # | B4: Challenge | C4: Task | D4: Success condition
A5: 1 | B5: Controls | C5: Create Scenario, Region, State, City, Category, Metric and Period dropdowns. | D5: All controls work; child lists react to parent selections.
A6: 2 | B6: INDEX + MATCH | C6: Return manager and region for the selected City. | D6: No hard-coded row number.
A7: 3 | B7: XLOOKUP | C7: Return Category, Unit Price and Supplier for the Top Product. | D7: Outputs change when Top Product changes.
A8: 4 | B8: OFFSET | C8: Create a dynamic trend range for a chart. | D8: Chart source can move/resize without manual rewiring.
A9: 5 | B9: INDIRECT | C9: Build Region → State → City dependent dropdowns. | D9: Selecting North changes State options; selecting Delhi changes City options.
A10: 6 | B10: CHOOSE + MATCH + INDEX | C10: Create one Metric switcher for Sales / Profit / Units. | D10: One control changes the KPI value.
A11: 7 | B11: Combined dashboard | C11: Build KPI cards + product chart + category mix + trend. | D11: Dashboard reacts to filters.
A12: 8 | B12: Business insight | C12: Identify the strongest region for the selected Metric and state one action. | D12: Conclusion is supported by the filtered data.
A13: 9 | B13: Stress test | C13: Try All + specific Region + specific State + specific City combinations. | D13: No broken references or stale outputs.
A14: 10 | B14: Performance thinking | C14: Explain why OFFSET and INDIRECT can become problematic at 100k+ rows. | D14: Propose INDEX/XLOOKUP/structured-reference alternatives where appropriate.
A17: FINAL CAPSTONE
A18: Build a one-page management dashboard where a manager selects Scenario, Region, State, City, Category and Metric, then sees dynamic KPIs, trend, category mix, top product and supporting lookup metadata. Add one written business recommendation based on the output.
