Workbook
Name Conversion_Pct: INDIRECT(Helper!$B$42)
Name F_1001: Top!$F$3
Name F_1002: Top!$F$4
Name F_1003: Top!$F$5
Name F_1004: Top!$F$6
Name Normal: Helper!$B$40
Name Poor: Helper!$B$39
Name SHOWME: INDIRECT([1]Data!$K$65)
Name SHOWME2: INDIRECT([1]Data!$K$83)
Name Superb: Helper!$B$41
Name Top_1: INDIRECT(Top!$N$3)
Name Top_2: INDIRECT(Top!$N$4)
Name Top_3: INDIRECT(Top!$N$5)
Name TopPerformer: INDIRECT([1]Data!$C$115)

Sheet Products
A1: ID | B1: Description | C1: Manufacturer | D1: Price | E1: Image
A2: 1001 | B2: Blue Socks | C2: Blue Marvel | D2: 5.45
A3: 1002 | B3: Pink Socks | C3: Pink Panther | D3: 5.75
A4: 1003 | B4: Red Socks | C4: Red Icon | D4: 4.95
A5: 1004 | B5: Orange Socks | C5: Orange Country | D5: 4.7

Sheet Orders
A1: ID | B1: Date | C1: Billing | D1: Amount | E1: Status
A2: 100100 | B2: 45646.417 | C2: Alexandria Hendrickson | D2: =SUMIF(Sold[Order],Orders!A2,Sold[Total]) -> 3310 | E2: Pending Payment
A3: 100099 | B3: 45646.375 | C3: Jerry Bellows | D3: =SUMIF(Sold[Order],Orders!A3,Sold[Total]) -> 705 | E3: On Hold
A4: 100098 | B4: 45631.292 | C4: Barry Jenkins | D4: =SUMIF(Sold[Order],Orders!A4,Sold[Total]) -> 1852.5 | E4: Processing
A5: 100097 | B5: 45627.458 | C5: Jeff Shepard | D5: =SUMIF(Sold[Order],Orders!A5,Sold[Total]) -> 2160 | E5: Completed
A6: 100096 | B6: 45613.458 | C6: Earl Barnes | D6: =SUMIF(Sold[Order],Orders!A6,Sold[Total]) -> 2270 | E6: Completed
A7: 100095 | B7: 45585.333 | C7: Lydia Andrews | D7: =SUMIF(Sold[Order],Orders!A7,Sold[Total]) -> 4844 | E7: Completed
A8: 100094 | B8: 45544.625 | C8: Taylor Logan | D8: =SUMIF(Sold[Order],Orders!A8,Sold[Total]) -> 7967.75 | E8: Completed
A9: 100093 | B9: 45507.583 | C9: John Doe | D9: =SUMIF(Sold[Order],Orders!A9,Sold[Total]) -> 4812.5 | E9: Completed
A10: 100092 | B10: 45495.375 | C10: Stephen Lowe | D10: =SUMIF(Sold[Order],Orders!A10,Sold[Total]) -> 3175 | E10: Completed
A11: 100091 | B11: 45463.333 | C11: Peyton Donahue | D11: =SUMIF(Sold[Order],Orders!A11,Sold[Total]) -> 3641 | E11: Completed
A12: 100090 | B12: 45422.333 | C12: Zev Mahoney | D12: =SUMIF(Sold[Order],Orders!A12,Sold[Total]) -> 3440.5 | E12: Completed
A13: 100089 | B13: 45395.458 | C13: Beckett Hughes | D13: =SUMIF(Sold[Order],Orders!A13,Sold[Total]) -> 4029.5 | E13: Completed
... A30: 100072 | B30: 44917.542 | C30: Mendel Oliver | D30: =SUMIF(Sold[Order],Orders!A30,Sold[Total]) -> 16380 | E30: Completed

Sheet Sold
A1: Order | B1: Date | C1: ID | D1: Product | E1: Qty | F1: Unit | G1: Total
A2: 100100 | B2: 45646.417 | C2: 1001 | D2: Blue Socks | E2: 100 | F2: 5.45 | G2: =E2*F2 -> 545
A3: 100100 | B3: 45646.417 | C3: 1002 | D3: Pink Socks | E3: 100 | F3: 5.75 | G3: =E3*F3 -> 575
A4: 100100 | B4: 45646.417 | C4: 1003 | D4: Red Socks | E4: 300 | F4: 4.95 | G4: =E4*F4 -> 1485
A5: 100100 | B5: 45646.417 | C5: 1004 | D5: Orange Socks | E5: 150 | F5: 4.7 | G5: =E5*F5 -> 705
A6: 100099 | B6: 45646.375 | C6: 1004 | D6: Orange Socks | E6: 150 | F6: 4.7 | G6: =E6*F6 -> 705
A7: 100098 | B7: 45631.292 | C7: 1003 | D7: Red Socks | E7: 200 | F7: 4.95 | G7: =E7*F7 -> 990
A8: 100098 | B8: 45631.292 | C8: 1004 | D8: Orange Socks | E8: 150 | F8: 5.75 | G8: =E8*F8 -> 862.5
A9: 100097 | B9: 45627.458 | C9: 1001 | D9: Blue Socks | E9: 200 | F9: 5.45 | G9: =E9*F9 -> 1090
A10: 100097 | B10: 45627.458 | C10: 1002 | D10: Pink Socks | E10: 100 | F10: 5.75 | G10: =E10*F10 -> 575
A11: 100097 | B11: 45627.458 | C11: 1003 | D11: Red Socks | E11: 100 | F11: 4.95 | G11: =E11*F11 -> 495
A12: 100096 | B12: 45613.458 | C12: 1002 | D12: Pink Socks | E12: 100 | F12: 5.75 | G12: =E12*F12 -> 575
A13: 100096 | B13: 45613.458 | C13: 1003 | D13: Red Socks | E13: 200 | F13: 4.95 | G13: =E13*F13 -> 990
... A82: 100072 | B82: 44917.542 | C82: 1001 | D82: Blue Socks | E82: 800 | F82: 4.7 | G82: =E82*F82 -> 3760

Sheet Expenses
A1: Year | B1: Month | C1: Expense | D1: Amount
A2: 2024 | B2: 12 | C2: Website Tech and Software | D2: 200
A3: 2024 | B3: 12 | C3: Inventory | D3: 850
A4: 2024 | B4: 12 | C4: Employees | D4: 600
A5: 2024 | B5: 12 | C5: Building | D5: 150
A6: 2024 | B6: 12 | C6: Shipping | D6: 650
A7: 2024 | B7: 11 | C7: Website Tech and Software | D7: 350
A8: 2024 | B8: 11 | C8: Inventory | D8: 850
A9: 2024 | B9: 11 | C9: Employees | D9: 600
A10: 2024 | B10: 11 | C10: Building | D10: 150
A11: 2024 | B11: 11 | C11: Shipping | D11: 450
A12: 2024 | B12: 10 | C12: Website Tech and Software | D12: 550
A13: 2024 | B13: 10 | C13: Inventory | D13: 1050
... A126: 2022 | B126: 12 | C126: Shipping | D126: 1500

Sheet Visitors
A1: Year | B1: Month | C1: Visitors
A2: 2024 | B2: 12 | C2: 6
A3: 2024 | B3: 11 | C3: 4
A4: 2024 | B4: 10 | C4: 2
A5: 2024 | B5: 9 | C5: 2
A6: 2024 | B6: 8 | C6: 2
A7: 2024 | B7: 7 | C7: 3
A8: 2024 | B8: 6 | C8: 2
A9: 2024 | B9: 5 | C9: 3
A10: 2024 | B10: 4 | C10: 2
A11: 2024 | B11: 3 | C11: 2
A12: 2024 | B12: 2 | C12: 1
A13: 2024 | B13: 1 | C13: 3
... A26: 2022 | B26: 12 | C26: 11

Sheet Helper
A1: Available Years for Selection | C1: Selected Year | D1: {=INDEX(A2:A3,C2,1)} -> 2024 | F1: SALES & EXPENSES CURRENT YEAR | K1: SALES & EXPENSES PREVIOUS YEAR
A2: 2023 | C2: 2 | F2: Year | G2: Month | H2: Sales | I2: Expenses | K2: Year | L2: Month | M2: Sales | N2: Expenses
A3: 2024 | F3: =$D$1 -> 2024 | G3: 12 | H3: {=SUMPRODUCT((YEAR(Sold[Date])=$D$1)*(MONTH(Sold[Date])=G3)*Sold[Total])} -> 8027.5 | I3: {=SUMPRODUCT((Expenses[Year]=$D$1)*(Expenses[Month]=G3)*Expenses[Amount])} -> 2450 | K3: =$D$1-1 -> 2023 | L3: 12 | M3: {=SUMPRODUCT((YEAR(Sold[Date])=$D$1-1)*(MONTH(Sold[Date])=L3)*Sold[Total])} -> 4510 | N3: {=SUMPRODUCT((Expenses[Year]=$D$1-1)*(Expenses[Month]=L3)*Expenses[Amount])} -> 2000
C4: Total Sales | D4: =H15 -> 53640.75 | F4: =$D$1 -> 2024 | G4: 11 | H4: {=SUMPRODUCT((YEAR(Sold[Date])=$D$1)*(MONTH(Sold[Date])=G4)*Sold[Total])} -> 2270 | I4: {=SUMPRODUCT((Expenses[Year]=$D$1)*(Expenses[Month]=G4)*Expenses[Amount])} -> 2400 | K4: =$D$1-1 -> 2023 | L4: 11 | M4: {=SUMPRODUCT((YEAR(Sold[Date])=$D$1-1)*(MONTH(Sold[Date])=L4)*Sold[Total])} -> 2898.5 | N4: {=SUMPRODUCT((Expenses[Year]=$D$1-1)*(Expenses[Month]=L4)*Expenses[Amount])} -> 2150
C5: Previous | D5: =M15 -> 43447.75 | F5: =$D$1 -> 2024 | G5: 10 | H5: {=SUMPRODUCT((YEAR(Sold[Date])=$D$1)*(MONTH(Sold[Date])=G5)*Sold[Total])} -> 4844 | I5: {=SUMPRODUCT((Expenses[Year]=$D$1)*(Expenses[Month]=G5)*Expenses[Amount])} -> 2800 | K5: =$D$1-1 -> 2023 | L5: 10 | M5: {=SUMPRODUCT((YEAR(Sold[Date])=$D$1-1)*(MONTH(Sold[Date])=L5)*Sold[Total])} -> 2927.75 | N5: {=SUMPRODUCT((Expenses[Year]=$D$1-1)*(Expenses[Month]=L5)*Expenses[Amount])} -> 2000
C6: Difference | D6: =IF(D5=0,"#NA",(D4-D5)/D5) -> 0.23460363 | F6: =$D$1 -> 2024 | G6: 9 | H6: {=SUMPRODUCT((YEAR(Sold[Date])=$D$1)*(MONTH(Sold[Date])=G6)*Sold[Total])} -> 7967.75 | I6: {=SUMPRODUCT((Expenses[Year]=$D$1)*(Expenses[Month]=G6)*Expenses[Amount])} -> 2500 | K6: =$D$1-1 -> 2023 | L6: 9 | M6: {=SUMPRODUCT((YEAR(Sold[Date])=$D$1-1)*(MONTH(Sold[Date])=L6)*Sold[Total])} -> 3687.5 | N6: {=SUMPRODUCT((Expenses[Year]=$D$1-1)*(Expenses[Month]=L6)*Expenses[Amount])} -> 2100
C7: Diff + | D7: =IF(D6>=0,D6,"") -> 0.23460363 | F7: =$D$1 -> 2024 | G7: 8 | H7: {=SUMPRODUCT((YEAR(Sold[Date])=$D$1)*(MONTH(Sold[Date])=G7)*Sold[Total])} -> 4812.5 | I7: {=SUMPRODUCT((Expenses[Year]=$D$1)*(Expenses[Month]=G7)*Expenses[Amount])} -> 1950 | K7: =$D$1-1 -> 2023 | L7: 8 | M7: {=SUMPRODUCT((YEAR(Sold[Date])=$D$1-1)*(MONTH(Sold[Date])=L7)*Sold[Total])} -> 2239.25 | N7: {=SUMPRODUCT((Expenses[Year]=$D$1-1)*(Expenses[Month]=L7)*Expenses[Amount])} -> 2100
C8: Diff - | D8: =IF(D6<0,D6,"") | F8: =$D$1 -> 2024 | G8: 7 | H8: {=SUMPRODUCT((YEAR(Sold[Date])=$D$1)*(MONTH(Sold[Date])=G8)*Sold[Total])} -> 3175 | I8: {=SUMPRODUCT((Expenses[Year]=$D$1)*(Expenses[Month]=G8)*Expenses[Amount])} -> 1800 | K8: =$D$1-1 -> 2023 | L8: 7 | M8: {=SUMPRODUCT((YEAR(Sold[Date])=$D$1-1)*(MONTH(Sold[Date])=L8)*Sold[Total])} -> 4606.5 | N8: {=SUMPRODUCT((Expenses[Year]=$D$1-1)*(Expenses[Month]=L8)*Expenses[Amount])} -> 2600
F9: =$D$1 -> 2024 | G9: 6 | H9: {=SUMPRODUCT((YEAR(Sold[Date])=$D$1)*(MONTH(Sold[Date])=G9)*Sold[Total])} -> 3641 | I9: {=SUMPRODUCT((Expenses[Year]=$D$1)*(Expenses[Month]=G9)*Expenses[Amount])} -> 2250 | K9: =$D$1-1 -> 2023 | L9: 6 | M9: {=SUMPRODUCT((YEAR(Sold[Date])=$D$1-1)*(MONTH(Sold[Date])=L9)*Sold[Total])} -> 4188.5 | N9: {=SUMPRODUCT((Expenses[Year]=$D$1-1)*(Expenses[Month]=L9)*Expenses[Amount])} -> 1850
F10: =$D$1 -> 2024 | G10: 5 | H10: {=SUMPRODUCT((YEAR(Sold[Date])=$D$1)*(MONTH(Sold[Date])=G10)*Sold[Total])} -> 3440.5 | I10: {=SUMPRODUCT((Expenses[Year]=$D$1)*(Expenses[Month]=G10)*Expenses[Amount])} -> 2350 | K10: =$D$1-1 -> 2023 | L10: 5 | M10: {=SUMPRODUCT((YEAR(Sold[Date])=$D$1-1)*(MONTH(Sold[Date])=L10)*Sold[Total])} -> 3021 | N10: {=SUMPRODUCT((Expenses[Year]=$D$1-1)*(Expenses[Month]=L10)*Expenses[Amount])} -> 1850
C11: Total Expenses | D11: =I15 -> 27950 | F11: =$D$1 -> 2024 | G11: 4 | H11: {=SUMPRODUCT((YEAR(Sold[Date])=$D$1)*(MONTH(Sold[Date])=G11)*Sold[Total])} -> 4029.5 | I11: {=SUMPRODUCT((Expenses[Year]=$D$1)*(Expenses[Month]=G11)*Expenses[Amount])} -> 2300 | K11: =$D$1-1 -> 2023 | L11: 4 | M11: {=SUMPRODUCT((YEAR(Sold[Date])=$D$1-1)*(MONTH(Sold[Date])=L11)*Sold[Total])} -> 2612.5 | N11: {=SUMPRODUCT((Expenses[Year]=$D$1-1)*(Expenses[Month]=L11)*Expenses[Amount])} -> 1750
C12: Previous | D12: =N15 -> 24500 | F12: =$D$1 -> 2024 | G12: 3 | H12: {=SUMPRODUCT((YEAR(Sold[Date])=$D$1)*(MONTH(Sold[Date])=G12)*Sold[Total])} -> 2896.5 | I12: {=SUMPRODUCT((Expenses[Year]=$D$1)*(Expenses[Month]=G12)*Expenses[Amount])} -> 2600 | K12: =$D$1-1 -> 2023 | L12: 3 | M12: {=SUMPRODUCT((YEAR(Sold[Date])=$D$1-1)*(MONTH(Sold[Date])=L12)*Sold[Total])} -> 4219.75 | N12: {=SUMPRODUCT((Expenses[Year]=$D$1-1)*(Expenses[Month]=L12)*Expenses[Amount])} -> 1800
C13: Difference | D13: =IF(D12=0,"#NA",(D11-D12)/D12) -> 0.14081633 | F13: =$D$1 -> 2024 | G13: 2 | H13: {=SUMPRODUCT((YEAR(Sold[Date])=$D$1)*(MONTH(Sold[Date])=G13)*Sold[Total])} -> 5618 | I13: {=SUMPRODUCT((Expenses[Year]=$D$1)*(Expenses[Month]=G13)*Expenses[Amount])} -> 2400 | K13: =$D$1-1 -> 2023 | L13: 2 | M13: {=SUMPRODUCT((YEAR(Sold[Date])=$D$1-1)*(MONTH(Sold[Date])=L13)*Sold[Total])} -> 5618 | N13: {=SUMPRODUCT((Expenses[Year]=$D$1-1)*(Expenses[Month]=L13)*Expenses[Amount])} -> 2200
C14: Diff + | D14: =IF(D13>=0,D13,"") -> 0.14081633 | F14: =$D$1 -> 2024 | G14: 1 | H14: {=SUMPRODUCT((YEAR(Sold[Date])=$D$1)*(MONTH(Sold[Date])=G14)*Sold[Total])} -> 2918.5 | I14: {=SUMPRODUCT((Expenses[Year]=$D$1)*(Expenses[Month]=G14)*Expenses[Amount])} -> 2150 | K14: =$D$1-1 -> 2023 | L14: 1 | M14: {=SUMPRODUCT((YEAR(Sold[Date])=$D$1-1)*(MONTH(Sold[Date])=L14)*Sold[Total])} -> 2918.5 | N14: {=SUMPRODUCT((Expenses[Year]=$D$1-1)*(Expenses[Month]=L14)*Expenses[Amount])} -> 2100
C15: Diff - | D15: =IF(D13<0,D13,"") | H15: =SUM(H3:H14) -> 53640.75 | I15: =SUM(I3:I14) -> 27950 | M15: =SUM(M3:M14) -> 43447.75 | N15: =SUM(N3:N14) -> 24500
C18: Total Visitors | D18: {=SUMPRODUCT((Visitors[Year]=$D$1)*Visitors[Visitors])} -> 32
C19: Previous | D19: {=SUMPRODUCT((Visitors[Year]=$D$1-1)*Visitors[Visitors])} -> 30
C20: Difference | D20: =IF(D19=0,"#NA",(D18-D19)/D19) -> 0.066666667
C21: Diff + | D21: =IF(D20>=0,D20,"") -> 0.066666667
C22: Diff - | D22: =IF(D20<0,D20,"")
C25: Total Orders | D25: =COUNTIFS(Orders[Date],">=01/01/"&$D$1,Orders[Date],"<12/31/"&$D$1) -> 15
C26: Previous | D26: =COUNTIFS(Orders[Date],">=01/01/"&$D$1-1,Orders[Date],"<12/31/"&$D$1-1) -> 13
C27: Difference | D27: =IF(D26=0,"#NA",(D25-D26)/D26) -> 0.15384615
C28: Diff + | D28: =IF(D27>=0,D27,"") -> 0.15384615
C29: Diff - | D29: =IF(D27<0,D27,"")
E31: To 100% | F31: Max
C32: Conversion | D32: =D25/D18 -> 0.46875 | E32: =1-D32 -> 0.53125 | F32: 1
C33: Previous | D33: =D26/D19 -> 0.43333333
C34: Difference | D34: =IF(D33=0,"#NA",(D32-D33)/D33) -> 0.081730769
C35: Diff + | D35: =IF(D34>=0,D34,"") -> 0.081730769
C36: Diff - | D36: =IF(D34<0,D34,"")
C39: Option Poor
C40: Option Normal
C41: Option Superb
A42: Current Conversion Rate: | B42: =IF(D32>0.45,IF(D32>0.55,"Superb", "Normal"),"Poor") -> Normal | D42: =B42&" Conversion Rate" -> Normal Conversion Rate
A43: Current Conversion Icon: | D43: =IF(D32>0.45,IF(D32>0.55,"This is outstanding!", "Keep it up!"),"Improvements are necessary") -> Keep it up!

Sheet Top
A1: NOT SORTED DATA | H1: SORTED DATA | P1: Image
A2: ID | B2: Description | C2: Manufacturer | D2: Qty | E2: Amount | F2: Image | H2: ID | I2: Description | J2: Manufacturer | K2: Qty | L2: Amount | M2: X | N2: Helper
A3: 1001 | B3: Blue Socks | C3: Blue Marvel | D3: {=SUMPRODUCT((YEAR(Sold[Date])=Helper!$D$1)*(Sold[ID]=A3)*Sold[Qty])} -> 2535 | E3: {=SUMPRODUCT((YEAR(Sold[Date])=Helper!$D$1)*(Sold[ID]=A3)*Sold[Total])} -> 13815.75 | H3: {=_xlfn._xlws.SORT(Top[],5,-1)} -> 1003 | I3: Red Socks | J3: Red Icon | K3: 3040 | L3: 15048 | M3: 0 | N3: ="F_"&H3 -> F_1003
A4: 1002 | B4: Pink Socks | C4: Pink Panther | D4: {=SUMPRODUCT((YEAR(Sold[Date])=Helper!$D$1)*(Sold[ID]=A4)*Sold[Qty])} -> 1710 | E4: {=SUMPRODUCT((YEAR(Sold[Date])=Helper!$D$1)*(Sold[ID]=A4)*Sold[Total])} -> 9832.5 | H4: 1004 | I4: Orange Socks | J4: Orange Country | K4: 3030 | L4: 14944.5 | M4: 0 | N4: ="F_"&H4 -> F_1004
A5: 1003 | B5: Red Socks | C5: Red Icon | D5: {=SUMPRODUCT((YEAR(Sold[Date])=Helper!$D$1)*(Sold[ID]=A5)*Sold[Qty])} -> 3040 | E5: {=SUMPRODUCT((YEAR(Sold[Date])=Helper!$D$1)*(Sold[ID]=A5)*Sold[Total])} -> 15048 | H5: 1001 | I5: Blue Socks | J5: Blue Marvel | K5: 2535 | L5: 13815.75 | M5: 0 | N5: ="F_"&H5 -> F_1001
A6: 1004 | B6: Orange Socks | C6: Orange Country | D6: {=SUMPRODUCT((YEAR(Sold[Date])=Helper!$D$1)*(Sold[ID]=A6)*Sold[Qty])} -> 3030 | E6: {=SUMPRODUCT((YEAR(Sold[Date])=Helper!$D$1)*(Sold[ID]=A6)*Sold[Total])} -> 14944.5 | H6: 1002 | I6: Pink Socks | J6: Pink Panther | K6: 1710 | L6: 9832.5 | M6: 0 | N6: ="F_"&H6 -> F_1002

Sheet Dashboard
K10: TOP SELLING PRODUCTS
K12: =Top!J3 -> Red Icon
L13: =Top!I3 -> Red Socks
L14: Units:
L15: =Top!K3 -> 3040
K17: =Top!L3 -> 15048
K19: =Top!J4 -> Orange Country
L20: =Top!I4 -> Orange Socks
L21: Units:
L22: =Top!K4 -> 3030
C24: LATEST ORDERS | K24: =Top!L4 -> 14944.5
C26: Order ID | D26: Date & Time | E26: Billing Name | F26: Amount | G26: Status | K26: =Top!J5 -> Blue Marvel
L27: =Top!I5 -> Blue Socks
C28: =Orders!A2 -> 100100 | D28: =Orders!B2 -> 45646.417 | E28: =Orders!C2 -> Alexandria Hendrickson | F28: =Orders!D2 -> 3310 | G28: =Orders!E2 -> Pending Payment | L28: Units:
C29: =Orders!A3 -> 100099 | D29: =Orders!B3 -> 45646.375 | E29: =Orders!C3 -> Jerry Bellows | F29: =Orders!D3 -> 705 | G29: =Orders!E3 -> On Hold | L29: =Top!K5 -> 2535
C30: =Orders!A4 -> 100098 | D30: =Orders!B4 -> 45631.292 | E30: =Orders!C4 -> Barry Jenkins | F30: =Orders!D4 -> 1852.5 | G30: =Orders!E4 -> Processing
C31: =Orders!A5 -> 100097 | D31: =Orders!B5 -> 45627.458 | E31: =Orders!C5 -> Jeff Shepard | F31: =Orders!D5 -> 2160 | G31: =Orders!E5 -> Completed | K31: =Top!L5 -> 13815.75
