Workbook

Sheet Data
A1: Credit Card info
A2: Card Holder | B2: Card Number | C2: Valid Thru
A3: JOHN DOE | B3: **** **** **** 0000 | C3: 11/26
A5: Starting Balance
A6: 1000 | E6: DATE | F6: TRANSACTION | G6: FROM/TO | H6: AMOUNT | I6: NOTE | J6: BALANCE
E7: 44927 | F7: Income | G7: MyCompany | H7: 4200 | I7: Salary - December 2022 | J7: =A6+H7 -> 5200
E8: 44928 | F8: Housing | G8: Vavilon LTD | H8: -105 | I8: Home maintenance | J8: =IF(E8, J7+H8, "") -> 5095
A9: Transaction Categories | C9: Selected Month | E9: 44929 | F9: Transportation | G9: Parkings | H9: -10 | I9: Parking | J9: =IF(E9, J8+H9, "") -> 5085
A10: Income | C10: =DASHBOARD!L2 -> 44927 | E10: 44930 | F10: Food | G10: McDonalds | H10: -40 | J10: =IF(E10, J9+H10, "") -> 5045
A11: Housing | C11: Begins | E11: 44931 | F11: Utilities | G11: Water Co | H11: -102 | I11: Water | J11: =IF(E11, J10+H11, "") -> 4943
A12: Transportation | C12: =C10 -> 44927 | E12: 44932 | F12: Insurance | G12: BeSafe LTD | H12: -350 | I12: Life Insurance | J12: =IF(E12, J11+H12, "") -> 4593
A13: Food | C13: Ends | E13: 44933 | F13: Medical & Healthcare | G13: St.Johns Hospital | H13: -500 | J13: =IF(E13, J12+H13, "") -> 4093
A14: Utilities | C14: =C12+_xlfn.SWITCH(MONTH($C$10), 1, 31, 2, IF(YEAR($C$10)=2024,29,28), 3, 31, 4, 30, 5, 31, 6, 30, 7, 31, 8, 31, 9, 30, 10, 31, 11, 30, 12, 31)-1 -> 44957 | E14: 44934 | F14: Saving & Investing | G14: Great Bank | H14: -220 | J14: =IF(E14, J13+H14, "") -> 3873
A15: Insurance | E15: 44935 | F15: Personal Spending | G15: Best Gym | H15: -55 | I15: Gym Membership | J15: =IF(E15, J14+H15, "") -> 3818
A16: Medical & Healthcare | E16: 44936 | F16: Recreation & Entertainment | G16: NY Nicks | H16: -182.4 | I16: Basketball Tickets | J16: =IF(E16, J15+H16, "") -> 3635.6
A17: Saving & Investing | E17: 44937 | F17: Miscellaneous | G17: Barber123 | H17: -35 | I17: Haircut | J17: =IF(E17, J16+H17, "") -> 3600.6
A18: Personal Spending | E18: 44943 | F18: Housing | G18: Benjamin Holes | H18: -800 | I18: Rent - January 2023 | J18: =IF(E18, J17+H18, "") -> 2800.6
A19: Recreation & Entertainment | E19: 44943 | F19: Transportation | G19: Mega Oil | H19: -120 | I19: Gas | J19: =IF(E19, J18+H19, "") -> 2680.6
A20: Miscellaneous | C20: SELECT MONTH | E20: 44944 | F20: Income | G20: PayMeMore | H20: 500 | I20: Freelance Job | J20: =IF(E20, J19+H20, "") -> 3180.6
C21: 44927 | E21: 44945 | F21: Personal Spending | G21: Mimi | H21: -250 | J21: =IF(E21, J20+H21, "") -> 2930.6
C22: 44958 | E22: 44946 | F22: Food | G22: Grocery X | H22: -20 | J22: =IF(E22, J21+H22, "") -> 2910.6
C23: 44986 | E23: 44946 | F23: Miscellaneous | G23: Company E | H23: -15 | J23: =IF(E23, J22+H23, "") -> 2895.6
E24: 44946 | F24: Food | G24: Grocery X | H24: -99.87 | J24: =IF(E24, J23+H24, "") -> 2795.73
E25: 44947 | F25: Personal Spending | G25: Bomber | H25: -20 | J25: =IF(E25, J24+H25, "") -> 2775.73
E26: 44947 | F26: Food | G26: Grocery X | H26: -10.28 | J26: =IF(E26, J25+H26, "") -> 2765.45
E27: 44947 | F27: Utilities | G27: Electro Storm | H27: -55 | I27: Electricity | J27: =IF(E27, J26+H27, "") -> 2710.45
E28: 44947 | F28: Miscellaneous | G28: Company A | H28: -56.17 | J28: =IF(E28, J27+H28, "") -> 2654.28
E29: 44948 | F29: Recreation & Entertainment | G29: Big Screen | H29: -40 | I29: Movies | J29: =IF(E29, J28+H29, "") -> 2614.28
E30: 44949 | F30: Miscellaneous | G30: Company A | H30: -512.44 | J30: =IF(E30, J29+H30, "") -> 2101.84
E31: 44949 | F31: Food | G31: Grocery Y | H31: -25 | J31: =IF(E31, J30+H31, "") -> 2076.84
E32: 44949 | F32: Personal Spending | G32: Extra Shop | H32: -15 | J32: =IF(E32, J31+H32, "") -> 2061.84
E33: 44949 | F33: Food | G33: Grocery Y | H33: -22.14 | J33: =IF(E33, J32+H33, "") -> 2039.7
E34: 44949 | F34: Personal Spending | G34: Gadget | H34: -55 | J34: =IF(E34, J33+H34, "") -> 1984.7
E35: 44951 | F35: Food | G35: Grocery Y | H35: -17.55 | J35: =IF(E35, J34+H35, "") -> 1967.15
E36: 44951 | F36: Miscellaneous | G36: Company B | H36: -52.22 | J36: =IF(E36, J35+H36, "") -> 1914.93
E37: 44951 | F37: Personal Spending | G37: Clothing Co | H37: -80 | J37: =IF(E37, J36+H37, "") -> 1834.93
E38: 44952 | F38: Food | G38: Grocery Y | H38: -105 | J38: =IF(E38, J37+H38, "") -> 1729.93
E39: 44952 | F39: Recreation & Entertainment | G39: Tantum | H39: -25 | J39: =IF(E39, J38+H39, "") -> 1704.93
E40: 44952 | F40: Food | G40: Grocery Z | H40: -54.47 | J40: =IF(E40, J39+H40, "") -> 1650.46
E41: 44953 | F41: Personal Spending | G41: Instant Shop | H41: -355.15 | J41: =IF(E41, J40+H41, "") -> 1295.31
E42: 44953 | F42: Miscellaneous | G42: Company C | H42: -41.25 | J42: =IF(E42, J41+H42, "") -> 1254.06
E43: 44953 | F43: Utilities | G43: World Web | H43: -70 | I43: Internet | J43: =IF(E43, J42+H43, "") -> 1184.06
E44: 44953 | F44: Miscellaneous | G44: Company D | H44: -69.77 | J44: =IF(E44, J43+H44, "") -> 1114.29
E45: 44954 | F45: Personal Spending | G45: Persona | H45: -35.36 | J45: =IF(E45, J44+H45, "") -> 1078.93
E46: 44954 | F46: Miscellaneous | G46: Company D | H46: -17.68 | J46: =IF(E46, J45+H46, "") -> 1061.25
E47: 44954 | F47: Personal Spending | G47: Persona | H47: -45.18 | J47: =IF(E47, J46+H47, "") -> 1016.07
E48: 44955 | F48: Food | G48: Grocery Z | H48: -75.25 | J48: =IF(E48, J47+H48, "") -> 940.82
E49: 44956 | F49: Personal Spending | G49: Clothing Co | H49: -62.17 | I49: Invoice #225626 | J49: =IF(E49, J48+H49, "") -> 878.65
E50: 44957 | F50: Food | G50: Grocery Z | H50: -21.14 | J50: =IF(E50, J49+H50, "") -> 857.51
E51: 44957 | F51: Income | G51: Roof Gang | H51: 350 | I51: Roofing Assistance | J51: =IF(E51, J50+H51, "") -> 1207.51
E52: 44957 | F52: Recreation & Entertainment | G52: Tai Mai | H52: -45.5 | I52: Massage | J52: =IF(E52, J51+H52, "") -> 1162.01
E53: 44957 | F53: Food | G53: Grocery Z | H53: -14.55 | J53: =IF(E53, J52+H53, "") -> 1147.46
E54: 44958 | F54: Income | G54: MyCompany | H54: 4200 | I54: Salary - January 2023 | J54: =IF(E54, J53+H54, "") -> 5347.46
E55: 44959 | F55: Housing | G55: Vavilon LTD | H55: -105 | I55: Home maintenance | J55: =IF(E55, J54+H55, "") -> 5242.46
E56: 44960 | F56: Transportation | G56: Lorem Ipsum | H56: -50 | J56: =IF(E56, J55+H56, "") -> 5192.46
E57: 44960 | F57: Food | G57: Lorem Ipsum | H57: -60 | J57: =IF(E57, J56+H57, "") -> 5132.46
E58: 44964 | F58: Utilities | G58: Lorem Ipsum | H58: -70 | J58: =IF(E58, J57+H58, "") -> 5062.46
E59: 44965 | F59: Insurance | G59: Lorem Ipsum | H59: -421.5 | J59: =IF(E59, J58+H59, "") -> 4640.96
E60: 44965 | F60: Medical & Healthcare | G60: Lorem Ipsum | H60: -302.25 | J60: =IF(E60, J59+H60, "") -> 4338.71
E61: 44966 | F61: Saving & Investing | G61: Lorem Ipsum | H61: -187.85 | J61: =IF(E61, J60+H61, "") -> 4150.86
E62: 44966 | F62: Personal Spending | G62: Lorem Ipsum | H62: -56 | J62: =IF(E62, J61+H62, "") -> 4094.86
E63: 44968 | F63: Recreation & Entertainment | G63: Lorem Ipsum | H63: -35 | J63: =IF(E63, J62+H63, "") -> 4059.86
E64: 44969 | F64: Miscellaneous | G64: Lorem Ipsum | H64: -222 | J64: =IF(E64, J63+H64, "") -> 3837.86
E65: 44969 | F65: Housing | G65: Lorem Ipsum | H65: -253.47 | J65: =IF(E65, J64+H65, "") -> 3584.39
E66: 44969 | F66: Transportation | G66: Lorem Ipsum | H66: -152 | J66: =IF(E66, J65+H66, "") -> 3432.39
E67: 44970 | F67: Personal Spending | G67: Lorem Ipsum | H67: -25 | J67: =IF(E67, J66+H67, "") -> 3407.39
... E78: 44979 | F78: Utilities | G78: Lorem Ipsum | H78: -95 | J78: =IF(E78, J77+H78, "") -> 1431.25
E79: 44980 | F79: Income | G79: PayMeMore | H79: 200 | I79: Freelance Job | J79: =IF(E79, J78+H79, "") -> 1631.25
E80: 44981 | F80: Recreation & Entertainment | G80: Lorem Ipsum | H80: -625 | J80: =IF(E80, J79+H80, "") -> 1006.25
E81: 44981 | F81: Miscellaneous | G81: Lorem Ipsum | H81: -45 | J81: =IF(E81, J80+H81, "") -> 961.25
E82: 44981 | F82: Food | G82: Lorem Ipsum | H82: -25 | J82: =IF(E82, J81+H82, "") -> 936.25
E83: 44983 | F83: Transportation | G83: Lorem Ipsum | H83: -55 | J83: =IF(E83, J82+H83, "") -> 881.25
E84: 44983 | F84: Recreation & Entertainment | G84: Lorem Ipsum | H84: -47 | J84: =IF(E84, J83+H84, "") -> 834.25
E85: 44983 | F85: Transportation | G85: Lorem Ipsum | H85: -11 | J85: =IF(E85, J84+H85, "") -> 823.25
E86: 44983 | F86: Income | G86: Birthday Co | H86: 300 | I86: Gift Card | J86: =IF(E86, J85+H86, "") -> 1123.25
E87: 44985 | F87: Recreation & Entertainment | G87: Lorem Ipsum | H87: -5.88 | J87: =IF(E87, J86+H87, "") -> 1117.37
E88: 44985 | F88: Transportation | G88: Lorem Ipsum | H88: -14 | J88: =IF(E88, J87+H88, "") -> 1103.37
E89: 44986 | F89: Income | G89: MyCompany | H89: 3600 | I89: Salary - February 2023 | J89: =IF(E89, J88+H89, "") -> 4703.37
E90: 44988 | F90: Housing | G90: Vavilon LTD | H90: -105 | I90: Home maintenance | J90: =IF(E90, J89+H90, "") -> 4598.37
E91: 44989 | F91: Food | G91: Lorem Ipsum | H91: -450 | J91: =IF(E91, J90+H91, "") -> 4148.37
E92: 44990 | F92: Utilities | G92: Lorem Ipsum | H92: -56 | J92: =IF(E92, J91+H92, "") -> 4092.37
E93: 44995 | F93: Insurance | G93: Lorem Ipsum | H93: -54.17 | J93: =IF(E93, J92+H93, "") -> 4038.2
E94: 44996 | F94: Medical & Healthcare | G94: Lorem Ipsum | H94: -99.99 | J94: =IF(E94, J93+H94, "") -> 3938.21
E95: 44996 | F95: Saving & Investing | G95: Lorem Ipsum | H95: -356 | J95: =IF(E95, J94+H95, "") -> 3582.21
E96: 44997 | F96: Personal Spending | G96: Lorem Ipsum | H96: -58.25 | J96: =IF(E96, J95+H96, "") -> 3523.96
E97: 44997 | F97: Recreation & Entertainment | G97: Lorem Ipsum | H97: -66.24 | J97: =IF(E97, J96+H97, "") -> 3457.72
E98: 45000 | F98: Miscellaneous | G98: Lorem Ipsum | H98: -72.15 | J98: =IF(E98, J97+H98, "") -> 3385.57
E99: 45000 | F99: Housing | G99: Lorem Ipsum | H99: -90 | J99: =IF(E99, J98+H99, "") -> 3295.57
E100: 45002 | F100: Transportation | G100: Lorem Ipsum | H100: -107 | J100: =IF(E100, J99+H100, "") -> 3188.57
E101: 45002 | F101: Miscellaneous | G101: Lorem Ipsum | H101: -25 | J101: =IF(E101, J100+H101, "") -> 3163.57
E102: 45002 | F102: Recreation & Entertainment | G102: Lorem Ipsum | H102: -45 | J102: =IF(E102, J101+H102, "") -> 3118.57
... E113: 45016 | F113: Miscellaneous | G113: Lorem Ipsum | H113: -424 | J113: =IF(E113, J112+H113, "") -> 1854.34
E114: 45017 | F114: Income | G114: MyCompany | H114: 4150 | I114: Salary - March 2023 | J114: =IF(E114, J113+H114, "") -> 6004.34
E115: 45019 | F115: Housing | G115: Vavilon LTD | H115: -105 | I115: Home maintenance | J115: =IF(E115, J114+H115, "") -> 5899.34
E116: 45020 | F116: Miscellaneous | G116: Lorem Ipsum | H116: -65.15 | J116: =IF(E116, J115+H116, "") -> 5834.19
J117: =IF(E117, J116+H117, "")
J118: =IF(E118, J117+H118, "")
J119: =IF(E119, J118+H119, "")
J120: =IF(E120, J119+H120, "")
J121: =IF(E121, J120+H121, "")
...

Sheet Calc
A1: Selected Month
A2: =DASHBOARD!L2 -> 44927
A3: Begins
A4: =A2 -> 44927 | D4: 6 LATEST INCOMES
A5: Ends | D5: DATE | E5: TRANSACTION | F5: FROM/TO | G5: AMOUNT
A6: =A4+_xlfn.SWITCH(MONTH($A$2), 1, 31, 2, IF(YEAR($A$2)=2024,29,28), 3, 31, 4, 30, 5, 31, 6, 30, 7, 31, 8, 31, 9, 30, 10, 31, 11, 30, 12, 31)-1 -> 44957 | D6: {=LARGE(IF(Table1[[#Data],[TRANSACTION]]="Income",Table1[[#Data],[DATE]]),1)} -> 45017 | E6: {=INDEX(Table1[[#Data],[TRANSACTION]],MATCH(1,(Table1[[#Data],[TRANSACTION]]="Income")*(Table1[[#Data],[DATE]]=Calc!D6),0))} -> Income | F6: {=INDEX(Table1[[#Data],[FROM/TO]],MATCH(1,(Table1[[#Data],[TRANSACTION]]="Income")*(Table1[[#Data],[DATE]]=Calc!D6),0))} -> MyCompany | G6: {=INDEX(Table1[[#Data],[AMOUNT]],MATCH(1,(Table1[[#Data],[TRANSACTION]]="Income")*(Table1[[#Data],[DATE]]=Calc!D6),0))} -> 4150
D7: {=LARGE(IF(Table1[[#Data],[TRANSACTION]]="Income",Table1[[#Data],[DATE]]),2)} -> 44986 | E7: {=INDEX(Table1[[#Data],[TRANSACTION]],MATCH(1,(Table1[[#Data],[TRANSACTION]]="Income")*(Table1[[#Data],[DATE]]=Calc!D7),0))} -> Income | F7: {=INDEX(Table1[[#Data],[FROM/TO]],MATCH(1,(Table1[[#Data],[TRANSACTION]]="Income")*(Table1[[#Data],[DATE]]=Calc!D7),0))} -> MyCompany | G7: {=INDEX(Table1[[#Data],[AMOUNT]],MATCH(1,(Table1[[#Data],[TRANSACTION]]="Income")*(Table1[[#Data],[DATE]]=Calc!D7),0))} -> 3600
D8: {=LARGE(IF(Table1[[#Data],[TRANSACTION]]="Income",Table1[[#Data],[DATE]]),3)} -> 44983 | E8: {=INDEX(Table1[[#Data],[TRANSACTION]],MATCH(1,(Table1[[#Data],[TRANSACTION]]="Income")*(Table1[[#Data],[DATE]]=Calc!D8),0))} -> Income | F8: {=INDEX(Table1[[#Data],[FROM/TO]],MATCH(1,(Table1[[#Data],[TRANSACTION]]="Income")*(Table1[[#Data],[DATE]]=Calc!D8),0))} -> Birthday Co | G8: {=INDEX(Table1[[#Data],[AMOUNT]],MATCH(1,(Table1[[#Data],[TRANSACTION]]="Income")*(Table1[[#Data],[DATE]]=Calc!D8),0))} -> 300
A9: Current Ballance | D9: {=LARGE(IF(Table1[[#Data],[TRANSACTION]]="Income",Table1[[#Data],[DATE]]),4)} -> 44980 | E9: {=INDEX(Table1[[#Data],[TRANSACTION]],MATCH(1,(Table1[[#Data],[TRANSACTION]]="Income")*(Table1[[#Data],[DATE]]=Calc!D9),0))} -> Income | F9: {=INDEX(Table1[[#Data],[FROM/TO]],MATCH(1,(Table1[[#Data],[TRANSACTION]]="Income")*(Table1[[#Data],[DATE]]=Calc!D9),0))} -> PayMeMore | G9: {=INDEX(Table1[[#Data],[AMOUNT]],MATCH(1,(Table1[[#Data],[TRANSACTION]]="Income")*(Table1[[#Data],[DATE]]=Calc!D9),0))} -> 200
A10: =INDEX(Data!J7:J10000,ROWS(Table1[]),1) -> 5834.19 | D10: {=LARGE(IF(Table1[[#Data],[TRANSACTION]]="Income",Table1[[#Data],[DATE]]),5)} -> 44958 | E10: {=INDEX(Table1[[#Data],[TRANSACTION]],MATCH(1,(Table1[[#Data],[TRANSACTION]]="Income")*(Table1[[#Data],[DATE]]=Calc!D10),0))} -> Income | F10: {=INDEX(Table1[[#Data],[FROM/TO]],MATCH(1,(Table1[[#Data],[TRANSACTION]]="Income")*(Table1[[#Data],[DATE]]=Calc!D10),0))} -> MyCompany | G10: {=INDEX(Table1[[#Data],[AMOUNT]],MATCH(1,(Table1[[#Data],[TRANSACTION]]="Income")*(Table1[[#Data],[DATE]]=Calc!D10),0))} -> 4200
D11: {=LARGE(IF(Table1[[#Data],[TRANSACTION]]="Income",Table1[[#Data],[DATE]]),6)} -> 44957 | E11: {=INDEX(Table1[[#Data],[TRANSACTION]],MATCH(1,(Table1[[#Data],[TRANSACTION]]="Income")*(Table1[[#Data],[DATE]]=Calc!D11),0))} -> Income | F11: {=INDEX(Table1[[#Data],[FROM/TO]],MATCH(1,(Table1[[#Data],[TRANSACTION]]="Income")*(Table1[[#Data],[DATE]]=Calc!D11),0))} -> Roof Gang | G11: {=INDEX(Table1[[#Data],[AMOUNT]],MATCH(1,(Table1[[#Data],[TRANSACTION]]="Income")*(Table1[[#Data],[DATE]]=Calc!D11),0))} -> 350
D13: Month: | H13: Month: | I13: Month:
D14: =$A$2 -> 44927 | H14: =$A$2 -> 44927 | I14: =$A$2 -> 44927
D15: EXPENSE TYPE | E15: AMOUNT | F15: TOTAL | H15: TOTAL INCOME | I15: MONTHLY BALANCE
D16: Housing | E16: =-SUMIFS(Table1[[#Data],[AMOUNT]], Table1[[#Data],[TRANSACTION]],"HOUSING",Table1[[#Data],[DATE]], ">="&Calc!$A$4, Table1[[#Data],[DATE]], "<="&Calc!$A$6) -> 905 | F16: =SUM(E16:E25) -> 4902.54 | H16: =SUMIFS(Table1[[#Data],[AMOUNT]], Table1[[#Data],[TRANSACTION]],"Income",Table1[[#Data],[DATE]], ">="&Calc!$A$4, Table1[[#Data],[DATE]], "<="&Calc!$A$6) -> 5050 | I16: =H16-F16 -> 147.46
D17: Transportation | E17: =-SUMIFS(Table1[[#Data],[AMOUNT]], Table1[[#Data],[TRANSACTION]],"TRANSPORTATION",Table1[[#Data],[DATE]], ">="&Calc!$A$4, Table1[[#Data],[DATE]], "<="&Calc!$A$6) -> 130
D18: Food | E18: =-SUMIFS(Table1[[#Data],[AMOUNT]], Table1[[#Data],[TRANSACTION]],"FOOD",Table1[[#Data],[DATE]], ">="&Calc!$A$4, Table1[[#Data],[DATE]], "<="&Calc!$A$6) -> 505.25
D19: Utilities | E19: =-SUMIFS(Table1[[#Data],[AMOUNT]], Table1[[#Data],[TRANSACTION]],"UTILITIES",Table1[[#Data],[DATE]], ">="&Calc!$A$4, Table1[[#Data],[DATE]], "<="&Calc!$A$6) -> 227
D20: Insurance | E20: =-SUMIFS(Table1[[#Data],[AMOUNT]], Table1[[#Data],[TRANSACTION]],"INSURANCE",Table1[[#Data],[DATE]], ">="&Calc!$A$4, Table1[[#Data],[DATE]], "<="&Calc!$A$6) -> 350
D21: Medical & Healthcare | E21: =-SUMIFS(Table1[[#Data],[AMOUNT]], Table1[[#Data],[TRANSACTION]],"Medical & Healthcare",Table1[[#Data],[DATE]], ">="&Calc!$A$4, Table1[[#Data],[DATE]], "<="&Calc!$A$6) -> 500
D22: Saving & Investing | E22: =-SUMIFS(Table1[[#Data],[AMOUNT]], Table1[[#Data],[TRANSACTION]],"Saving & Investing",Table1[[#Data],[DATE]], ">="&Calc!$A$4, Table1[[#Data],[DATE]], "<="&Calc!$A$6) -> 220
D23: Personal Spending | E23: =-SUMIFS(Table1[[#Data],[AMOUNT]], Table1[[#Data],[TRANSACTION]],"Personal Spending",Table1[[#Data],[DATE]], ">="&Calc!$A$4, Table1[[#Data],[DATE]], "<="&Calc!$A$6) -> 972.86
D24: Recreation & Entertainment | E24: =-SUMIFS(Table1[[#Data],[AMOUNT]], Table1[[#Data],[TRANSACTION]],"Recreation & Entertainment ",Table1[[#Data],[DATE]], ">="&Calc!$A$4, Table1[[#Data],[DATE]], "<="&Calc!$A$6) -> 292.9
D25: Miscellaneous | E25: =-SUMIFS(Table1[[#Data],[AMOUNT]], Table1[[#Data],[TRANSACTION]],"Miscellaneous",Table1[[#Data],[DATE]], ">="&Calc!$A$4, Table1[[#Data],[DATE]], "<="&Calc!$A$6) -> 799.53
D28: 10 LATEST BALANCE DATA
D29: DATE | E29: BALANCE | F29: BALANCE (Round) | G29: BALANCE (K)
D30: =INDEX(Table1[[#Data],[DATE]],ROWS(Table1[])-10) -> 45007 | E30: =INDEX(Data!$J$7:$J$10000,ROWS(Table1[])-9) -> 2835.34 | F30: =ROUND(E30,-1) -> 2840 | G30: =F30/1000 -> 2.84
D31: =INDEX(Table1[[#Data],[DATE]],ROWS(Table1[])-9) -> 45008 | E31: =INDEX(Data!$J$7:$J$10000,ROWS(Table1[])-8) -> 2818.34 | F31: =ROUND(E31,-1) -> 2820 | G31: =F31/1000 -> 2.82
D32: =INDEX(Table1[[#Data],[DATE]],ROWS(Table1[])-8) -> 45009 | E32: =INDEX(Data!$J$7:$J$10000,ROWS(Table1[])-7) -> 2786.34 | F32: =ROUND(E32,-1) -> 2790 | G32: =F32/1000 -> 2.79
D33: =INDEX(Table1[[#Data],[DATE]],ROWS(Table1[])-7) -> 45009 | E33: =INDEX(Data!$J$7:$J$10000,ROWS(Table1[])-6) -> 2753.34 | F33: =ROUND(E33,-1) -> 2750 | G33: =F33/1000 -> 2.75
D34: =INDEX(Table1[[#Data],[DATE]],ROWS(Table1[])-6) -> 45009 | E34: =INDEX(Data!$J$7:$J$10000,ROWS(Table1[])-5) -> 2728.34 | F34: =ROUND(E34,-1) -> 2730 | G34: =F34/1000 -> 2.73
D35: =INDEX(Table1[[#Data],[DATE]],ROWS(Table1[])-5) -> 45013 | E35: =INDEX(Data!$J$7:$J$10000,ROWS(Table1[])-4) -> 2278.34 | F35: =ROUND(E35,-1) -> 2280 | G35: =F35/1000 -> 2.28
D36: =INDEX(Table1[[#Data],[DATE]],ROWS(Table1[])-4) -> 45014 | E36: =INDEX(Data!$J$7:$J$10000,ROWS(Table1[])-3) -> 1854.34 | F36: =ROUND(E36,-1) -> 1850 | G36: =F36/1000 -> 1.85
D37: =INDEX(Table1[[#Data],[DATE]],ROWS(Table1[])-3) -> 45016 | E37: =INDEX(Data!$J$7:$J$10000,ROWS(Table1[])-2) -> 6004.34 | F37: =ROUND(E37,-1) -> 6000 | G37: =F37/1000 -> 6
D38: =INDEX(Table1[[#Data],[DATE]],ROWS(Table1[])-1) -> 45019 | E38: =INDEX(Data!$J$7:$J$10000,ROWS(Table1[])-1) -> 5899.34 | F38: =ROUND(E38,-1) -> 5900 | G38: =F38/1000 -> 5.9
D39: =INDEX(Table1[[#Data],[DATE]],ROWS(Table1[])) -> 45020 | E39: =INDEX(Data!$J$7:$J$10000,ROWS(Table1[])) -> 5834.19 | F39: =ROUND(E39,-1) -> 5830 | G39: =F39/1000 -> 5.83

Sheet DASHBOARD
J2: Selected Month: | L2: 44927
B6: LATEST INCOME
B8: =Calc!D5 -> DATE | D8: =Calc!E5 -> TRANSACTION | F8: =Calc!F5 -> FROM/TO | H8: =Calc!G5 -> AMOUNT
B10: =Calc!D6 -> 45017 | D10: =Calc!E6 -> Income | F10: =Calc!F6 -> MyCompany | H10: =Calc!G6 -> 4150
B11: =Calc!D7 -> 44986 | D11: =Calc!E7 -> Income | F11: =Calc!F7 -> MyCompany | H11: =Calc!G7 -> 3600
B12: =Calc!D8 -> 44983 | D12: =Calc!E8 -> Income | F12: =Calc!F8 -> Birthday Co | H12: =Calc!G8 -> 300
B13: =Calc!D9 -> 44980 | D13: =Calc!E9 -> Income | F13: =Calc!F9 -> PayMeMore | H13: =Calc!G9 -> 200
B14: =Calc!D10 -> 44958 | D14: =Calc!E10 -> Income | F14: =Calc!F10 -> MyCompany | H14: =Calc!G10 -> 4200
B15: =Calc!D11 -> 44957 | D15: =Calc!E11 -> Income | F15: =Calc!F11 -> Roof Gang | H15: =Calc!G11 -> 350
